Workbook

Sheet Notes
B1: Aster Ridge (Demo) - .H Model - Notes
B2: Last updated 2026-07-29. Read before using this model.
B4: SYNTHETIC DEMO DATA
B5: Aster Ridge Senior Living is a FICTIONAL community. Every figure in this workbook is
B6: fabricated for a public process demonstration - see FABRICATION-SPEC.md in the deal folder.
B7: No real deal data anywhere in this file.
B9: MAPPING RULINGS - pipeline agents, 2026-07-29 demo build
B11: Pooled payroll taxes and benefits
B12: Operator GL pools 6710 Payroll Taxes / 6720 Employee Benefits company-wide (no department
B13: split). RULING: mapped to Benefits - Admin (no company-wide tag on the master list).
B14: IMPACT: departmental Benefits roll-up rows read 0; the full ,527/yr sits in Benefits -
B15: Admin; the payroll-burden metric is pooled-safe by construction (reads 16.85%). Do not
... B32: demo (no broker to query).

Sheet Aster Ridge.H (Review)
S2: 1 | T2: 2 | U2: 4
S3: T12 | T3: T6 | U3: T3
S4: =F5 -> 45869 | T4: =+EOMONTH(S4,6) -> 46053 | U4: =+EOMONTH(T4,3) -> 46142
F5: 45869 | G5: =EOMONTH(F5,1) -> 45900 | H5: =EOMONTH(G5,1) -> 45930 | I5: =EOMONTH(H5,1) -> 45961 | J5: =EOMONTH(I5,1) -> 45991 | K5: =EOMONTH(J5,1) -> 46022 | L5: =EOMONTH(K5,1) -> 46053 | M5: =EOMONTH(L5,1) -> 46081 | N5: =EOMONTH(M5,1) -> 46112 | ... Q5: =EOMONTH(P5,1) -> 46203 | S5: =Q5 -> 46203 | T5: =+S5 -> 46203 | U5: =+T5 -> 46203
D7: Days | F7: =DAY(EOMONTH(F5,0)) -> 31 | G7: =DAY(EOMONTH(G5,0)) -> 31 | H7: =DAY(EOMONTH(H5,0)) -> 30 | I7: =DAY(EOMONTH(I5,0)) -> 31 | J7: =DAY(EOMONTH(J5,0)) -> 30 | K7: =DAY(EOMONTH(K5,0)) -> 31 | L7: =DAY(EOMONTH(L5,0)) -> 31 | M7: =DAY(EOMONTH(M5,0)) -> 28 | ... Q7: =DAY(EOMONTH(Q5,0)) -> 30 | S7: =IFERROR(SUMIFS($E7:$Q7,$E$5:$Q$5,">="&S$4,$E$5:$Q$5,"<="&S$5),0)*S$2 -> 365 | T7: =IFERROR(SUMIFS($E7:$Q7,$E$5:$Q$5,">="&T$4,$E$5:$Q$5,"<="&T$5),0)*T$2 -> 362 | U7: =IFERROR(SUMIFS($E7:$Q7,$E$5:$Q$5,">="&U$4,$E$5:$Q$5,"<="&U$5),0)*U$2 -> 364
C9: Capacity | D9: IL | F9: =Census!E24 -> 40 | G9: =Census!F24 -> 40 | H9: =Census!G24 -> 40 | I9: =Census!H24 -> 40 | J9: =Census!I24 -> 40 | K9: =Census!J24 -> 40 | L9: =Census!K24 -> 40 | M9: =Census!L24 -> 40 | ... Q9: =Census!P24 -> 40 | S9: =+IFERROR(AVERAGEIFS($E9:$Q9,$E$5:$Q$5,">="&S$4,$E$5:$Q$5,"<="&S$5),"NA") -> 40 | T9: =+IFERROR(AVERAGEIFS($E9:$Q9,$E$5:$Q$5,">="&T$4,$E$5:$Q$5,"<="&T$5),"NA") -> 40 | U9: =+IFERROR(AVERAGEIFS($E9:$Q9,$E$5:$Q$5,">="&U$4,$E$5:$Q$5,"<="&U$5),"NA") -> 40
C10: Capacity | D10: AL | F10: =Census!E25 -> 30 | G10: =Census!F25 -> 30 | H10: =Census!G25 -> 30 | I10: =Census!H25 -> 30 | J10: =Census!I25 -> 30 | K10: =Census!J25 -> 30 | L10: =Census!K25 -> 30 | M10: =Census!L25 -> 30 | ... Q10: =Census!P25 -> 30 | S10: =+IFERROR(AVERAGEIFS($E10:$Q10,$E$5:$Q$5,">="&S$4,$E$5:$Q$5,"<="&S$5),"NA") -> 30 | T10: =+IFERROR(AVERAGEIFS($E10:$Q10,$E$5:$Q$5,">="&T$4,$E$5:$Q$5,"<="&T$5),"NA") -> 30 | U10: =+IFERROR(AVERAGEIFS($E10:$Q10,$E$5:$Q$5,">="&U$4,$E$5:$Q$5,"<="&U$5),"NA") -> 30
C11: Capacity | D11: MC | F11: =Census!E26 -> 14 | G11: =Census!F26 -> 14 | H11: =Census!G26 -> 14 | I11: =Census!H26 -> 14 | J11: =Census!I26 -> 14 | K11: =Census!J26 -> 14 | L11: =Census!K26 -> 14 | M11: =Census!L26 -> 14 | ... Q11: =Census!P26 -> 14 | S11: =+IFERROR(AVERAGEIFS($E11:$Q11,$E$5:$Q$5,">="&S$4,$E$5:$Q$5,"<="&S$5),"NA") -> 14 | T11: =+IFERROR(AVERAGEIFS($E11:$Q11,$E$5:$Q$5,">="&T$4,$E$5:$Q$5,"<="&T$5),"NA") -> 14 | U11: =+IFERROR(AVERAGEIFS($E11:$Q11,$E$5:$Q$5,">="&U$4,$E$5:$Q$5,"<="&U$5),"NA") -> 14
C12: Capacity | D12: Total | F12: =SUM(F9:F11) -> 84 | G12: =SUM(G9:G11) -> 84 | H12: =SUM(H9:H11) -> 84 | I12: =SUM(I9:I11) -> 84 | J12: =SUM(J9:J11) -> 84 | K12: =SUM(K9:K11) -> 84 | L12: =SUM(L9:L11) -> 84 | M12: =SUM(M9:M11) -> 84 | ... Q12: =SUM(Q9:Q11) -> 84 | S12: =+AVERAGEIFS($E12:$Q12,$E$5:$Q$5,">="&S$4,$E$5:$Q$5,"<="&S$5) -> 84 | T12: =+AVERAGEIFS($E12:$Q12,$E$5:$Q$5,">="&T$4,$E$5:$Q$5,"<="&T$5) -> 84 | U12: =+AVERAGEIFS($E12:$Q12,$E$5:$Q$5,">="&U$4,$E$5:$Q$5,"<="&U$5) -> 84
C14: Occupied | D14: IL | F14: =F19*F9 -> 34 | G14: =G19*G9 -> 34 | H14: =H19*H9 -> 35 | I14: =I19*I9 -> 35 | J14: =J19*J9 -> 36 | K14: =K19*K9 -> 36 | L14: =L19*L9 -> 36 | M14: =M19*M9 -> 35 | ... Q14: =Q19*Q9 -> 37 | S14: =+IFERROR(AVERAGEIFS($E14:$Q14,$E$5:$Q$5,">="&S$4,$E$5:$Q$5,"<="&S$5),"NA") -> 35.583333 | T14: =+IFERROR(AVERAGEIFS($E14:$Q14,$E$5:$Q$5,">="&T$4,$E$5:$Q$5,"<="&T$5),"NA") -> 36.166667 | U14: =+IFERROR(AVERAGEIFS($E14:$Q14,$E$5:$Q$5,">="&U$4,$E$5:$Q$5,"<="&U$5),"NA") -> 36.666667
C15: Occupied | D15: AL | F15: =F20*F10 -> 26 | G15: =G20*G10 -> 27 | H15: =H20*H10 -> 27 | I15: =I20*I10 -> 26 | J15: =J20*J10 -> 27 | K15: =K20*K10 -> 28 | L15: =L20*L10 -> 28 | M15: =M20*M10 -> 27 | ... Q15: =Q20*Q10 -> 28 | S15: =+IFERROR(AVERAGEIFS($E15:$Q15,$E$5:$Q$5,">="&S$4,$E$5:$Q$5,"<="&S$5),"NA") -> 27.25 | T15: =+IFERROR(AVERAGEIFS($E15:$Q15,$E$5:$Q$5,">="&T$4,$E$5:$Q$5,"<="&T$5),"NA") -> 27.666667 | U15: =+IFERROR(AVERAGEIFS($E15:$Q15,$E$5:$Q$5,">="&U$4,$E$5:$Q$5,"<="&U$5),"NA") -> 28
C16: Occupied | D16: MC | F16: =F21*F11 -> 11 | G16: =G21*G11 -> 12 | H16: =H21*H11 -> 12 | I16: =I21*I11 -> 12 | J16: =J21*J11 -> 13 | K16: =K21*K11 -> 12 | L16: =L21*L11 -> 12 | M16: =M21*M11 -> 13 | ... Q16: =Q21*Q11 -> 13 | S16: =+IFERROR(AVERAGEIFS($E16:$Q16,$E$5:$Q$5,">="&S$4,$E$5:$Q$5,"<="&S$5),"NA") -> 12.333333 | T16: =+IFERROR(AVERAGEIFS($E16:$Q16,$E$5:$Q$5,">="&T$4,$E$5:$Q$5,"<="&T$5),"NA") -> 12.666667 | U16: =+IFERROR(AVERAGEIFS($E16:$Q16,$E$5:$Q$5,">="&U$4,$E$5:$Q$5,"<="&U$5),"NA") -> 12.666667
C17: Occupied | D17: Total | F17: =SUM(F14:F16) -> 71 | G17: =SUM(G14:G16) -> 73 | H17: =SUM(H14:H16) -> 74 | I17: =SUM(I14:I16) -> 73 | J17: =SUM(J14:J16) -> 76 | K17: =SUM(K14:K16) -> 76 | L17: =SUM(L14:L16) -> 76 | M17: =SUM(M14:M16) -> 75 | ... Q17: =SUM(Q14:Q16) -> 78 | S17: =+AVERAGEIFS($E17:$Q17,$E$5:$Q$5,">="&S$4,$E$5:$Q$5,"<="&S$5) -> 75.166667 | T17: =+AVERAGEIFS($E17:$Q17,$E$5:$Q$5,">="&T$4,$E$5:$Q$5,"<="&T$5) -> 76.5 | U17: =+AVERAGEIFS($E17:$Q17,$E$5:$Q$5,">="&U$4,$E$5:$Q$5,"<="&U$5) -> 77.333333
C19: Occ % | D19: IL | F19: =Census!E34 -> 0.85 | G19: =Census!F34 -> 0.85 | H19: =Census!G34 -> 0.875 | I19: =Census!H34 -> 0.875 | J19: =Census!I34 -> 0.9 | K19: =Census!J34 -> 0.9 | L19: =Census!K34 -> 0.9 | M19: =Census!L34 -> 0.875 | ... Q19: =Census!P34 -> 0.925 | S19: =+IFERROR(S14/S9,"NA") -> 0.88958333 | T19: =+IFERROR(T14/T9,"NA") -> 0.90416667 | U19: =+IFERROR(U14/U9,"NA") -> 0.91666667
C20: Occ % | D20: AL | F20: =Census!E35 -> 0.86666667 | G20: =Census!F35 -> 0.9 | H20: =Census!G35 -> 0.9 | I20: =Census!H35 -> 0.86666667 | J20: =Census!I35 -> 0.9 | K20: =Census!J35 -> 0.93333333 | L20: =Census!K35 -> 0.93333333 | M20: =Census!L35 -> 0.9 | ... Q20: =Census!P35 -> 0.93333333 | S20: =+IFERROR(S15/S10,"NA") -> 0.90833333 | T20: =+IFERROR(T15/T10,"NA") -> 0.92222222 | U20: =+IFERROR(U15/U10,"NA") -> 0.93333333
C21: Occ % | D21: MC | F21: =Census!E36 -> 0.78571429 | G21: =Census!F36 -> 0.85714286 | H21: =Census!G36 -> 0.85714286 | I21: =Census!H36 -> 0.85714286 | J21: =Census!I36 -> 0.92857143 | K21: =Census!J36 -> 0.85714286 | L21: =Census!K36 -> 0.85714286 | M21: =Census!L36 -> 0.92857143 | ... Q21: =Census!P36 -> 0.92857143 | S21: =+IFERROR(S16/S11,"NA") -> 0.88095238 | T21: =+IFERROR(T16/T11,"NA") -> 0.9047619 | U21: =+IFERROR(U16/U11,"NA") -> 0.9047619
C22: Occ % | D22: Total | F22: =+IFERROR(F17/F12,"NA") -> 0.8452381 | G22: =+IFERROR(G17/G12,"NA") -> 0.86904762 | H22: =+IFERROR(H17/H12,"NA") -> 0.88095238 | I22: =+IFERROR(I17/I12,"NA") -> 0.86904762 | J22: =+IFERROR(J17/J12,"NA") -> 0.9047619 | K22: =+IFERROR(K17/K12,"NA") -> 0.9047619 | L22: =+IFERROR(L17/L12,"NA") -> 0.9047619 | M22: =+IFERROR(M17/M12,"NA") -> 0.89285714 | ... Q22: =+IFERROR(Q17/Q12,"NA") -> 0.92857143 | S22: =+IFERROR(S17/S12,"NA") -> 0.89484127 | T22: =+IFERROR(T17/T12,"NA") -> 0.91071429 | U22: =+IFERROR(U17/U12,"NA") -> 0.92063492
D24: PRD | F24: =+F17*F7*F199 -> 2201 | G24: =+G17*G7*G199 -> 2263 | H24: =+H17*H7*H199 -> 2220 | I24: =+I17*I7*I199 -> 2263 | J24: =+J17*J7*J199 -> 2280 | K24: =+K17*K7*K199 -> 2356 | L24: =+L17*L7*L199 -> 2356 | M24: =+M17*M7*M199 -> 2100 | ... Q24: =+Q17*Q7*Q199 -> 2340 | S24: =IFERROR(SUMIFS($E24:$Q24,$E$5:$Q$5,">="&S$4,$E$5:$Q$5,"<="&S$5),0)*S$2 -> 27433 | T24: =IFERROR(SUMIFS($E24:$Q24,$E$5:$Q$5,">="&T$4,$E$5:$Q$5,"<="&T$5),0)*T$2 -> 27700 | U24: =IFERROR(SUMIFS($E24:$Q24,$E$5:$Q$5,">="&U$4,$E$5:$Q$5,"<="&U$5),0)*U$2 -> 28152
D26: REVENUE
B28: =_xlfn.LET(_xlpm.r,_xlfn.XLOOKUP(D28,'AR PnL Mapping'!$C$3:$C$60,'AR PnL Mapping'!$B$3:$B$60,""),IF(OR(_xlpm.r="",_xlpm.r=0),"",_xlpm.r)) -> Rent Revenue - IL | D28: 4010 - Rent Income - IL | F28: =_xlfn.XLOOKUP($D28,'AR Historical Financials'!$C$8:$C$93,'AR Historical Financials'!E$8:E$93) -> 130152 | G28: =_xlfn.XLOOKUP($D28,'AR Historical Financials'!$C$8:$C$93,'AR Historical Financials'!F$8:F$93) -> 130398 | H28: =_xlfn.XLOOKUP($D28,'AR Historical Financials'!$C$8:$C$93,'AR Historical Financials'!G$8:G$93) -> 133507 | I28: =_xlfn.XLOOKUP($D28,'AR Historical Financials'!$C$8:$C$93,'AR Historical Financials'!H$8:H$93) -> 132350 | J28: =_xlfn.XLOOKUP($D28,'AR Historical Financials'!$C$8:$C$93,'AR Historical Financials'!I$8:I$93) -> 135400 | K28: =_xlfn.XLOOKUP($D28,'AR Historical Financials'!$C$8:$C$93,'AR Historical Financials'!J$8:J$93) -> 135680 | L28: =_xlfn.XLOOKUP($D28,'AR Historical Financials'!$C$8:$C$93,'AR Historical Financials'!K$8:K$93) -> 136760 | M28: =_xlfn.XLOOKUP($D28,'AR Historical Financials'!$C$8:$C$93,'AR Historical Financials'!L$8:L$93) -> 133994 | ... Q28: =_xlfn.XLOOKUP($D28,'AR Historical Financials'!$C$8:$C$93,'AR Historical Financials'!P$8:P$93) -> 140535 | S28: =IFERROR(SUMIFS($E28:$Q28,$E$5:$Q$5,">="&S$4,$E$5:$Q$5,"<="&S$5),0)*S$2 -> 1624031 | T28: =IFERROR(SUMIFS($E28:$Q28,$E$5:$Q$5,">="&T$4,$E$5:$Q$5,"<="&T$5),0)*T$2 -> 1653088 | U28: =IFERROR(SUMIFS($E28:$Q28,$E$5:$Q$5,">="&U$4,$E$5:$Q$5,"<="&U$5),0)*U$2 -> 1670908
B29: =_xlfn.LET(_xlpm.r,_xlfn.XLOOKUP(D29,'AR PnL Mapping'!$C$3:$C$60,'AR PnL Mapping'!$B$3:$B$60,""),IF(OR(_xlpm.r="",_xlpm.r=0),"",_xlpm.r)) -> Rent Revenue - AL | D29: 4020 - Rent Income - AL | F29: =_xlfn.XLOOKUP($D29,'AR Historical Financials'!$C$8:$C$93,'AR Historical Financials'!E$8:E$93) -> 120910 | G29: =_xlfn.XLOOKUP($D29,'AR Historical Financials'!$C$8:$C$93,'AR Historical Financials'!F$8:F$93) -> 125160 | H29: =_xlfn.XLOOKUP($D29,'AR Historical Financials'!$C$8:$C$93,'AR Historical Financials'!G$8:G$93) -> 124124 | I29: =_xlfn.XLOOKUP($D29,'AR Historical Financials'!$C$8:$C$93,'AR Historical Financials'!H$8:H$93) -> 118673 | J29: =_xlfn.XLOOKUP($D29,'AR Historical Financials'!$C$8:$C$93,'AR Historical Financials'!I$8:I$93) -> 123170 | K29: =_xlfn.XLOOKUP($D29,'AR Historical Financials'!$C$8:$C$93,'AR Historical Financials'!J$8:J$93) -> 128565 | L29: =_xlfn.XLOOKUP($D29,'AR Historical Financials'!$C$8:$C$93,'AR Historical Financials'!K$8:K$93) -> 129671 | M29: =_xlfn.XLOOKUP($D29,'AR Historical Financials'!$C$8:$C$93,'AR Historical Financials'!L$8:L$93) -> 125562 | ... Q29: =_xlfn.XLOOKUP($D29,'AR Historical Financials'!$C$8:$C$93,'AR Historical Financials'!P$8:P$93) -> 128925 | S29: =IFERROR(SUMIFS($E29:$Q29,$E$5:$Q$5,">="&S$4,$E$5:$Q$5,"<="&S$5),0)*S$2 -> 1506396 | T29: =IFERROR(SUMIFS($E29:$Q29,$E$5:$Q$5,">="&T$4,$E$5:$Q$5,"<="&T$5),0)*T$2 -> 1531588 | U29: =IFERROR(SUMIFS($E29:$Q29,$E$5:$Q$5,">="&U$4,$E$5:$Q$5,"<="&U$5),0)*U$2 -> 1541664
B30: =_xlfn.LET(_xlpm.r,_xlfn.XLOOKUP(D30,'AR PnL Mapping'!$C$3:$C$60,'AR PnL Mapping'!$B$3:$B$60,""),IF(OR(_xlpm.r="",_xlpm.r=0),"",_xlpm.r)) -> Rent Revenue - MC | D30: 4030 - Rent Income - MC | F30: =_xlfn.XLOOKUP($D30,'AR Historical Financials'!$C$8:$C$93,'AR Historical Financials'!E$8:E$93) -> 86707 | G30: =_xlfn.XLOOKUP($D30,'AR Historical Financials'!$C$8:$C$93,'AR Historical Financials'!F$8:F$93) -> 93912 | H30: =_xlfn.XLOOKUP($D30,'AR Historical Financials'!$C$8:$C$93,'AR Historical Financials'!G$8:G$93) -> 93135 | I30: =_xlfn.XLOOKUP($D30,'AR Historical Financials'!$C$8:$C$93,'AR Historical Financials'!H$8:H$93) -> 92846 | J30: =_xlfn.XLOOKUP($D30,'AR Historical Financials'!$C$8:$C$93,'AR Historical Financials'!I$8:I$93) -> 101036 | K30: =_xlfn.XLOOKUP($D30,'AR Historical Financials'!$C$8:$C$93,'AR Historical Financials'!J$8:J$93) -> 94072 | L30: =_xlfn.XLOOKUP($D30,'AR Historical Financials'!$C$8:$C$93,'AR Historical Financials'!K$8:K$93) -> 94660 | M30: =_xlfn.XLOOKUP($D30,'AR Historical Financials'!$C$8:$C$93,'AR Historical Financials'!L$8:L$93) -> 102463 | ... Q30: =_xlfn.XLOOKUP($D30,'AR Historical Financials'!$C$8:$C$93,'AR Historical Financials'!P$8:P$93) -> 101595 | S30: =IFERROR(SUMIFS($E30:$Q30,$E$5:$Q$5,">="&S$4,$E$5:$Q$5,"<="&S$5),0)*S$2 -> 1155856 | T30: =IFERROR(SUMIFS($E30:$Q30,$E$5:$Q$5,">="&T$4,$E$5:$Q$5,"<="&T$5),0)*T$2 -> 1188296 | U30: =IFERROR(SUMIFS($E30:$Q30,$E$5:$Q$5,">="&U$4,$E$5:$Q$5,"<="&U$5),0)*U$2 -> 1181216
B32: =_xlfn.LET(_xlpm.r,_xlfn.XLOOKUP(D32,'AR PnL Mapping'!$C$3:$C$60,'AR PnL Mapping'!$B$3:$B$60,""),IF(OR(_xlpm.r="",_xlpm.r=0),"",_xlpm.r)) | D32: TOTAL RENT REVENUE | F32: =_xlfn.XLOOKUP($D32,'AR Historical Financials'!$C$8:$C$93,'AR Historical Financials'!E$8:E$93) -> 337769 | G32: =_xlfn.XLOOKUP($D32,'AR Historical Financials'!$C$8:$C$93,'AR Historical Financials'!F$8:F$93) -> 349470 | H32: =_xlfn.XLOOKUP($D32,'AR Historical Financials'!$C$8:$C$93,'AR Historical Financials'!G$8:G$93) -> 350766 | I32: =_xlfn.XLOOKUP($D32,'AR Historical Financials'!$C$8:$C$93,'AR Historical Financials'!H$8:H$93) -> 343869 | J32: =_xlfn.XLOOKUP($D32,'AR Historical Financials'!$C$8:$C$93,'AR Historical Financials'!I$8:I$93) -> 359606 | K32: =_xlfn.XLOOKUP($D32,'AR Historical Financials'!$C$8:$C$93,'AR Historical Financials'!J$8:J$93) -> 358317 | L32: =_xlfn.XLOOKUP($D32,'AR Historical Financials'!$C$8:$C$93,'AR Historical Financials'!K$8:K$93) -> 361091 | M32: =_xlfn.XLOOKUP($D32,'AR Historical Financials'!$C$8:$C$93,'AR Historical Financials'!L$8:L$93) -> 362019 | ... Q32: =_xlfn.XLOOKUP($D32,'AR Historical Financials'!$C$8:$C$93,'AR Historical Financials'!P$8:P$93) -> 371055 | S32: =IFERROR(SUMIFS($E32:$Q32,$E$5:$Q$5,">="&S$4,$E$5:$Q$5,"<="&S$5),0)*S$2 -> 4286283 | T32: =IFERROR(SUMIFS($E32:$Q32,$E$5:$Q$5,">="&T$4,$E$5:$Q$5,"<="&T$5),0)*T$2 -> 4372972 | U32: =IFERROR(SUMIFS($E32:$Q32,$E$5:$Q$5,">="&U$4,$E$5:$Q$5,"<="&U$5),0)*U$2 -> 4393788
B34: =_xlfn.LET(_xlpm.r,_xlfn.XLOOKUP(D34,'AR PnL Mapping'!$C$3:$C$60,'AR PnL Mapping'!$B$3:$B$60,""),IF(OR(_xlpm.r="",_xlpm.r=0),"",_xlpm.r)) -> Care Revenue - AL | D34: 4110 - Care Level Income - AL | F34: =_xlfn.XLOOKUP($D34,'AR Historical Financials'!$C$8:$C$93,'AR Historical Financials'!E$8:E$93) -> 25794 | G34: =_xlfn.XLOOKUP($D34,'AR Historical Financials'!$C$8:$C$93,'AR Historical Financials'!F$8:F$93) -> 26554 | H34: =_xlfn.XLOOKUP($D34,'AR Historical Financials'!$C$8:$C$93,'AR Historical Financials'!G$8:G$93) -> 26411 | I34: =_xlfn.XLOOKUP($D34,'AR Historical Financials'!$C$8:$C$93,'AR Historical Financials'!H$8:H$93) -> 25486 | J34: =_xlfn.XLOOKUP($D34,'AR Historical Financials'!$C$8:$C$93,'AR Historical Financials'!I$8:I$93) -> 26677 | K34: =_xlfn.XLOOKUP($D34,'AR Historical Financials'!$C$8:$C$93,'AR Historical Financials'!J$8:J$93) -> 27880 | L34: =_xlfn.XLOOKUP($D34,'AR Historical Financials'!$C$8:$C$93,'AR Historical Financials'!K$8:K$93) -> 27928 | M34: =_xlfn.XLOOKUP($D34,'AR Historical Financials'!$C$8:$C$93,'AR Historical Financials'!L$8:L$93) -> 26782 | ... Q34: =_xlfn.XLOOKUP($D34,'AR Historical Financials'!$C$8:$C$93,'AR Historical Financials'!P$8:P$93) -> 27660 | S34: =IFERROR(SUMIFS($E34:$Q34,$E$5:$Q$5,">="&S$4,$E$5:$Q$5,"<="&S$5),0)*S$2 -> 322560 | T34: =IFERROR(SUMIFS($E34:$Q34,$E$5:$Q$5,">="&T$4,$E$5:$Q$5,"<="&T$5),0)*T$2 -> 327516 | U34: =IFERROR(SUMIFS($E34:$Q34,$E$5:$Q$5,">="&U$4,$E$5:$Q$5,"<="&U$5),0)*U$2 -> 329992
B35: =_xlfn.LET(_xlpm.r,_xlfn.XLOOKUP(D35,'AR PnL Mapping'!$C$3:$C$60,'AR PnL Mapping'!$B$3:$B$60,""),IF(OR(_xlpm.r="",_xlpm.r=0),"",_xlpm.r)) -> Care Revenue - MC | D35: 4120 - Care Level Income - MC | F35: =_xlfn.XLOOKUP($D35,'AR Historical Financials'!$C$8:$C$93,'AR Historical Financials'!E$8:E$93) -> 15207 | G35: =_xlfn.XLOOKUP($D35,'AR Historical Financials'!$C$8:$C$93,'AR Historical Financials'!F$8:F$93) -> 16471 | H35: =_xlfn.XLOOKUP($D35,'AR Historical Financials'!$C$8:$C$93,'AR Historical Financials'!G$8:G$93) -> 16462 | I35: =_xlfn.XLOOKUP($D35,'AR Historical Financials'!$C$8:$C$93,'AR Historical Financials'!H$8:H$93) -> 16569 | J35: =_xlfn.XLOOKUP($D35,'AR Historical Financials'!$C$8:$C$93,'AR Historical Financials'!I$8:I$93) -> 18104 | K35: =_xlfn.XLOOKUP($D35,'AR Historical Financials'!$C$8:$C$93,'AR Historical Financials'!J$8:J$93) -> 16781 | L35: =_xlfn.XLOOKUP($D35,'AR Historical Financials'!$C$8:$C$93,'AR Historical Financials'!K$8:K$93) -> 16726 | M35: =_xlfn.XLOOKUP($D35,'AR Historical Financials'!$C$8:$C$93,'AR Historical Financials'!L$8:L$93) -> 17969 | ... Q35: =_xlfn.XLOOKUP($D35,'AR Historical Financials'!$C$8:$C$93,'AR Historical Financials'!P$8:P$93) -> 18000 | S35: =IFERROR(SUMIFS($E35:$Q35,$E$5:$Q$5,">="&S$4,$E$5:$Q$5,"<="&S$5),0)*S$2 -> 204547 | T35: =IFERROR(SUMIFS($E35:$Q35,$E$5:$Q$5,">="&T$4,$E$5:$Q$5,"<="&T$5),0)*T$2 -> 209906 | U35: =IFERROR(SUMIFS($E35:$Q35,$E$5:$Q$5,">="&U$4,$E$5:$Q$5,"<="&U$5),0)*U$2 -> 209664
B37: =_xlfn.LET(_xlpm.r,_xlfn.XLOOKUP(D37,'AR PnL Mapping'!$C$3:$C$60,'AR PnL Mapping'!$B$3:$B$60,""),IF(OR(_xlpm.r="",_xlpm.r=0),"",_xlpm.r)) | D37: TOTAL CARE REVENUE | F37: =_xlfn.XLOOKUP($D37,'AR Historical Financials'!$C$8:$C$93,'AR Historical Financials'!E$8:E$93) -> 41001 | G37: =_xlfn.XLOOKUP($D37,'AR Historical Financials'!$C$8:$C$93,'AR Historical Financials'!F$8:F$93) -> 43025 | H37: =_xlfn.XLOOKUP($D37,'AR Historical Financials'!$C$8:$C$93,'AR Historical Financials'!G$8:G$93) -> 42873 | I37: =_xlfn.XLOOKUP($D37,'AR Historical Financials'!$C$8:$C$93,'AR Historical Financials'!H$8:H$93) -> 42055 | J37: =_xlfn.XLOOKUP($D37,'AR Historical Financials'!$C$8:$C$93,'AR Historical Financials'!I$8:I$93) -> 44781 | K37: =_xlfn.XLOOKUP($D37,'AR Historical Financials'!$C$8:$C$93,'AR Historical Financials'!J$8:J$93) -> 44661 | L37: =_xlfn.XLOOKUP($D37,'AR Historical Financials'!$C$8:$C$93,'AR Historical Financials'!K$8:K$93) -> 44654 | M37: =_xlfn.XLOOKUP($D37,'AR Historical Financials'!$C$8:$C$93,'AR Historical Financials'!L$8:L$93) -> 44751 | ... Q37: =_xlfn.XLOOKUP($D37,'AR Historical Financials'!$C$8:$C$93,'AR Historical Financials'!P$8:P$93) -> 45660 | S37: =IFERROR(SUMIFS($E37:$Q37,$E$5:$Q$5,">="&S$4,$E$5:$Q$5,"<="&S$5),0)*S$2 -> 527107 | T37: =IFERROR(SUMIFS($E37:$Q37,$E$5:$Q$5,">="&T$4,$E$5:$Q$5,"<="&T$5),0)*T$2 -> 537422 | U37: =IFERROR(SUMIFS($E37:$Q37,$E$5:$Q$5,">="&U$4,$E$5:$Q$5,"<="&U$5),0)*U$2 -> 539656
B39: =_xlfn.LET(_xlpm.r,_xlfn.XLOOKUP(D39,'AR PnL Mapping'!$C$3:$C$60,'AR PnL Mapping'!$B$3:$B$60,""),IF(OR(_xlpm.r="",_xlpm.r=0),"",_xlpm.r)) -> Rent - Second Person | D39: 4210 - Second Person Fees | F39: =_xlfn.XLOOKUP($D39,'AR Historical Financials'!$C$8:$C$93,'AR Historical Financials'!E$8:E$93) -> 7297 | G39: =_xlfn.XLOOKUP($D39,'AR Historical Financials'!$C$8:$C$93,'AR Historical Financials'!F$8:F$93) -> 7396 | H39: =_xlfn.XLOOKUP($D39,'AR Historical Financials'!$C$8:$C$93,'AR Historical Financials'!G$8:G$93) -> 7551 | I39: =_xlfn.XLOOKUP($D39,'AR Historical Financials'!$C$8:$C$93,'AR Historical Financials'!H$8:H$93) -> 7493 | J39: =_xlfn.XLOOKUP($D39,'AR Historical Financials'!$C$8:$C$93,'AR Historical Financials'!I$8:I$93) -> 7787 | K39: =_xlfn.XLOOKUP($D39,'AR Historical Financials'!$C$8:$C$93,'AR Historical Financials'!J$8:J$93) -> 7905 | L39: =_xlfn.XLOOKUP($D39,'AR Historical Financials'!$C$8:$C$93,'AR Historical Financials'!K$8:K$93) -> 7847 | M39: =_xlfn.XLOOKUP($D39,'AR Historical Financials'!$C$8:$C$93,'AR Historical Financials'!L$8:L$93) -> 7539 | ... Q39: =_xlfn.XLOOKUP($D39,'AR Historical Financials'!$C$8:$C$93,'AR Historical Financials'!P$8:P$93) -> 7960 | S39: =IFERROR(SUMIFS($E39:$Q39,$E$5:$Q$5,">="&S$4,$E$5:$Q$5,"<="&S$5),0)*S$2 -> 92194 | T39: =IFERROR(SUMIFS($E39:$Q39,$E$5:$Q$5,">="&T$4,$E$5:$Q$5,"<="&T$5),0)*T$2 -> 93530 | U39: =IFERROR(SUMIFS($E39:$Q39,$E$5:$Q$5,">="&U$4,$E$5:$Q$5,"<="&U$5),0)*U$2 -> 94964
B40: =_xlfn.LET(_xlpm.r,_xlfn.XLOOKUP(D40,'AR PnL Mapping'!$C$3:$C$60,'AR PnL Mapping'!$B$3:$B$60,""),IF(OR(_xlpm.r="",_xlpm.r=0),"",_xlpm.r)) -> Community Fees | D40: 4310 - Community Fees | F40: =_xlfn.XLOOKUP($D40,'AR Historical Financials'!$C$8:$C$93,'AR Historical Financials'!E$8:E$93) -> 4087 | G40: =_xlfn.XLOOKUP($D40,'AR Historical Financials'!$C$8:$C$93,'AR Historical Financials'!F$8:F$93) -> 9901 | H40: =_xlfn.XLOOKUP($D40,'AR Historical Financials'!$C$8:$C$93,'AR Historical Financials'!G$8:G$93) -> 5616 | I40: =_xlfn.XLOOKUP($D40,'AR Historical Financials'!$C$8:$C$93,'AR Historical Financials'!H$8:H$93) -> 3000 | J40: =_xlfn.XLOOKUP($D40,'AR Historical Financials'!$C$8:$C$93,'AR Historical Financials'!I$8:I$93) -> 13391 | K40: =_xlfn.XLOOKUP($D40,'AR Historical Financials'!$C$8:$C$93,'AR Historical Financials'!J$8:J$93) -> 3969 | L40: =_xlfn.XLOOKUP($D40,'AR Historical Financials'!$C$8:$C$93,'AR Historical Financials'!K$8:K$93) -> 3000 | M40: =_xlfn.XLOOKUP($D40,'AR Historical Financials'!$C$8:$C$93,'AR Historical Financials'!L$8:L$93) -> 3000 | ... Q40: =_xlfn.XLOOKUP($D40,'AR Historical Financials'!$C$8:$C$93,'AR Historical Financials'!P$8:P$93) -> 3000 | S40: =IFERROR(SUMIFS($E40:$Q40,$E$5:$Q$5,">="&S$4,$E$5:$Q$5,"<="&S$5),0)*S$2 -> 69359 | T40: =IFERROR(SUMIFS($E40:$Q40,$E$5:$Q$5,">="&T$4,$E$5:$Q$5,"<="&T$5),0)*T$2 -> 58790 | U40: =IFERROR(SUMIFS($E40:$Q40,$E$5:$Q$5,">="&U$4,$E$5:$Q$5,"<="&U$5),0)*U$2 -> 67860
B41: =_xlfn.LET(_xlpm.r,_xlfn.XLOOKUP(D41,'AR PnL Mapping'!$C$3:$C$60,'AR PnL Mapping'!$B$3:$B$60,""),IF(OR(_xlpm.r="",_xlpm.r=0),"",_xlpm.r)) -> Other Revenue | D41: 4410 - Other Resident Income | F41: =_xlfn.XLOOKUP($D41,'AR Historical Financials'!$C$8:$C$93,'AR Historical Financials'!E$8:E$93) -> 3577 | G41: =_xlfn.XLOOKUP($D41,'AR Historical Financials'!$C$8:$C$93,'AR Historical Financials'!F$8:F$93) -> 3254 | H41: =_xlfn.XLOOKUP($D41,'AR Historical Financials'!$C$8:$C$93,'AR Historical Financials'!G$8:G$93) -> 2852 | I41: =_xlfn.XLOOKUP($D41,'AR Historical Financials'!$C$8:$C$93,'AR Historical Financials'!H$8:H$93) -> 2960 | J41: =_xlfn.XLOOKUP($D41,'AR Historical Financials'!$C$8:$C$93,'AR Historical Financials'!I$8:I$93) -> 3420 | K41: =_xlfn.XLOOKUP($D41,'AR Historical Financials'!$C$8:$C$93,'AR Historical Financials'!J$8:J$93) -> 3557 | L41: =_xlfn.XLOOKUP($D41,'AR Historical Financials'!$C$8:$C$93,'AR Historical Financials'!K$8:K$93) -> 3171 | M41: =_xlfn.XLOOKUP($D41,'AR Historical Financials'!$C$8:$C$93,'AR Historical Financials'!L$8:L$93) -> 2827 | ... Q41: =_xlfn.XLOOKUP($D41,'AR Historical Financials'!$C$8:$C$93,'AR Historical Financials'!P$8:P$93) -> 3091 | S41: =IFERROR(SUMIFS($E41:$Q41,$E$5:$Q$5,">="&S$4,$E$5:$Q$5,"<="&S$5),0)*S$2 -> 38740 | T41: =IFERROR(SUMIFS($E41:$Q41,$E$5:$Q$5,">="&T$4,$E$5:$Q$5,"<="&T$5),0)*T$2 -> 38240 | U41: =IFERROR(SUMIFS($E41:$Q41,$E$5:$Q$5,">="&U$4,$E$5:$Q$5,"<="&U$5),0)*U$2 -> 40372
B42: =_xlfn.LET(_xlpm.r,_xlfn.XLOOKUP(D42,'AR PnL Mapping'!$C$3:$C$60,'AR PnL Mapping'!$B$3:$B$60,""),IF(OR(_xlpm.r="",_xlpm.r=0),"",_xlpm.r)) -> Other Revenue | D42: 4510 - Guest Meals & Ancillary | F42: =_xlfn.XLOOKUP($D42,'AR Historical Financials'!$C$8:$C$93,'AR Historical Financials'!E$8:E$93) -> 2517 | G42: =_xlfn.XLOOKUP($D42,'AR Historical Financials'!$C$8:$C$93,'AR Historical Financials'!F$8:F$93) -> 1915 | H42: =_xlfn.XLOOKUP($D42,'AR Historical Financials'!$C$8:$C$93,'AR Historical Financials'!G$8:G$93) -> 2183 | I42: =_xlfn.XLOOKUP($D42,'AR Historical Financials'!$C$8:$C$93,'AR Historical Financials'!H$8:H$93) -> 2715 | J42: =_xlfn.XLOOKUP($D42,'AR Historical Financials'!$C$8:$C$93,'AR Historical Financials'!I$8:I$93) -> 2310 | K42: =_xlfn.XLOOKUP($D42,'AR Historical Financials'!$C$8:$C$93,'AR Historical Financials'!J$8:J$93) -> 1882 | L42: =_xlfn.XLOOKUP($D42,'AR Historical Financials'!$C$8:$C$93,'AR Historical Financials'!K$8:K$93) -> 2397 | M42: =_xlfn.XLOOKUP($D42,'AR Historical Financials'!$C$8:$C$93,'AR Historical Financials'!L$8:L$93) -> 2693 | ... Q42: =_xlfn.XLOOKUP($D42,'AR Historical Financials'!$C$8:$C$93,'AR Historical Financials'!P$8:P$93) -> 2568 | S42: =IFERROR(SUMIFS($E42:$Q42,$E$5:$Q$5,">="&S$4,$E$5:$Q$5,"<="&S$5),0)*S$2 -> 27826 | T42: =IFERROR(SUMIFS($E42:$Q42,$E$5:$Q$5,">="&T$4,$E$5:$Q$5,"<="&T$5),0)*T$2 -> 28608 | U42: =IFERROR(SUMIFS($E42:$Q42,$E$5:$Q$5,">="&U$4,$E$5:$Q$5,"<="&U$5),0)*U$2 -> 28448
B44: =_xlfn.LET(_xlpm.r,_xlfn.XLOOKUP(D44,'AR PnL Mapping'!$C$3:$C$60,'AR PnL Mapping'!$B$3:$B$60,""),IF(OR(_xlpm.r="",_xlpm.r=0),"",_xlpm.r)) | D44: TOTAL OTHER REVENUE | F44: =_xlfn.XLOOKUP($D44,'AR Historical Financials'!$C$8:$C$93,'AR Historical Financials'!E$8:E$93) -> 17478 | G44: =_xlfn.XLOOKUP($D44,'AR Historical Financials'!$C$8:$C$93,'AR Historical Financials'!F$8:F$93) -> 22466 | H44: =_xlfn.XLOOKUP($D44,'AR Historical Financials'!$C$8:$C$93,'AR Historical Financials'!G$8:G$93) -> 18202 | I44: =_xlfn.XLOOKUP($D44,'AR Historical Financials'!$C$8:$C$93,'AR Historical Financials'!H$8:H$93) -> 16168 | J44: =_xlfn.XLOOKUP($D44,'AR Historical Financials'!$C$8:$C$93,'AR Historical Financials'!I$8:I$93) -> 26908 | K44: =_xlfn.XLOOKUP($D44,'AR Historical Financials'!$C$8:$C$93,'AR Historical Financials'!J$8:J$93) -> 17313 | L44: =_xlfn.XLOOKUP($D44,'AR Historical Financials'!$C$8:$C$93,'AR Historical Financials'!K$8:K$93) -> 16415 | M44: =_xlfn.XLOOKUP($D44,'AR Historical Financials'!$C$8:$C$93,'AR Historical Financials'!L$8:L$93) -> 16059 | ... Q44: =_xlfn.XLOOKUP($D44,'AR Historical Financials'!$C$8:$C$93,'AR Historical Financials'!P$8:P$93) -> 16619 | S44: =IFERROR(SUMIFS($E44:$Q44,$E$5:$Q$5,">="&S$4,$E$5:$Q$5,"<="&S$5),0)*S$2 -> 228119 | T44: =IFERROR(SUMIFS($E44:$Q44,$E$5:$Q$5,">="&T$4,$E$5:$Q$5,"<="&T$5),0)*T$2 -> 219168 | U44: =IFERROR(SUMIFS($E44:$Q44,$E$5:$Q$5,">="&U$4,$E$5:$Q$5,"<="&U$5),0)*U$2 -> 231644
... B112: =_xlfn.LET(_xlpm.r,_xlfn.XLOOKUP(D112,'AR PnL Mapping'!$C$3:$C$60,'AR PnL Mapping'!$B$3:$B$60,""),IF(OR(_xlpm.r="",_xlpm.r=0),"",_xlpm.r)) | D112: NET OPERATING INCOME | F112: =_xlfn.XLOOKUP($D112,'AR Historical Financials'!$C$8:$C$93,'AR Historical Financials'!E$8:E$93) -> 110425 | G112: =_xlfn.XLOOKUP($D112,'AR Historical Financials'!$C$8:$C$93,'AR Historical Financials'!F$8:F$93) -> 128635 | H112: =_xlfn.XLOOKUP($D112,'AR Historical Financials'!$C$8:$C$93,'AR Historical Financials'!G$8:G$93) -> 128564 | I112: =_xlfn.XLOOKUP($D112,'AR Historical Financials'!$C$8:$C$93,'AR Historical Financials'!H$8:H$93) -> 120208 | J112: =_xlfn.XLOOKUP($D112,'AR Historical Financials'!$C$8:$C$93,'AR Historical Financials'!I$8:I$93) -> 146294 | K112: =_xlfn.XLOOKUP($D112,'AR Historical Financials'!$C$8:$C$93,'AR Historical Financials'!J$8:J$93) -> 132565 | L112: =_xlfn.XLOOKUP($D112,'AR Historical Financials'!$C$8:$C$93,'AR Historical Financials'!K$8:K$93) -> 132911 | M112: =_xlfn.XLOOKUP($D112,'AR Historical Financials'!$C$8:$C$93,'AR Historical Financials'!L$8:L$93) -> 134889 | ... Q112: =_xlfn.XLOOKUP($D112,'AR Historical Financials'!$C$8:$C$93,'AR Historical Financials'!P$8:P$93) -> 146787 | S112: =IFERROR(SUMIFS($E112:$Q112,$E$5:$Q$5,">="&S$4,$E$5:$Q$5,"<="&S$5),0)*S$2 -> 1614832 | T112: =IFERROR(SUMIFS($E112:$Q112,$E$5:$Q$5,">="&T$4,$E$5:$Q$5,"<="&T$5),0)*T$2 -> 1696282 | U112: =IFERROR(SUMIFS($E112:$Q112,$E$5:$Q$5,">="&U$4,$E$5:$Q$5,"<="&U$5),0)*U$2 -> 1748728
B116: AL Rent | C116: Rent Revenue - AL | F116: =+SUMIFS(F$25:F$113,$B$25:$B$113,$C116) -> 120910 | G116: =+SUMIFS(G$25:G$113,$B$25:$B$113,$C116) -> 125160 | H116: =+SUMIFS(H$25:H$113,$B$25:$B$113,$C116) -> 124124 | I116: =+SUMIFS(I$25:I$113,$B$25:$B$113,$C116) -> 118673 | J116: =+SUMIFS(J$25:J$113,$B$25:$B$113,$C116) -> 123170 | K116: =+SUMIFS(K$25:K$113,$B$25:$B$113,$C116) -> 128565 | L116: =+SUMIFS(L$25:L$113,$B$25:$B$113,$C116) -> 129671 | M116: =+SUMIFS(M$25:M$113,$B$25:$B$113,$C116) -> 125562 | ... Q116: =+SUMIFS(Q$25:Q$113,$B$25:$B$113,$C116) -> 128925 | S116: =IFERROR(SUMIFS($E116:$Q116,$E$5:$Q$5,">="&S$4,$E$5:$Q$5,"<="&S$5),0)*S$2 -> 1506396 | T116: =IFERROR(SUMIFS($E116:$Q116,$E$5:$Q$5,">="&T$4,$E$5:$Q$5,"<="&T$5),0)*T$2 -> 1531588 | U116: =IFERROR(SUMIFS($E116:$Q116,$E$5:$Q$5,">="&U$4,$E$5:$Q$5,"<="&U$5),0)*U$2 -> 1541664
B117: IL Rent | C117: Rent Revenue - IL | F117: =+SUMIFS(F$25:F$113,$B$25:$B$113,$C117) -> 130152 | G117: =+SUMIFS(G$25:G$113,$B$25:$B$113,$C117) -> 130398 | H117: =+SUMIFS(H$25:H$113,$B$25:$B$113,$C117) -> 133507 | I117: =+SUMIFS(I$25:I$113,$B$25:$B$113,$C117) -> 132350 | J117: =+SUMIFS(J$25:J$113,$B$25:$B$113,$C117) -> 135400 | K117: =+SUMIFS(K$25:K$113,$B$25:$B$113,$C117) -> 135680 | L117: =+SUMIFS(L$25:L$113,$B$25:$B$113,$C117) -> 136760 | M117: =+SUMIFS(M$25:M$113,$B$25:$B$113,$C117) -> 133994 | ... Q117: =+SUMIFS(Q$25:Q$113,$B$25:$B$113,$C117) -> 140535 | S117: =IFERROR(SUMIFS($E117:$Q117,$E$5:$Q$5,">="&S$4,$E$5:$Q$5,"<="&S$5),0)*S$2 -> 1624031 | T117: =IFERROR(SUMIFS($E117:$Q117,$E$5:$Q$5,">="&T$4,$E$5:$Q$5,"<="&T$5),0)*T$2 -> 1653088 | U117: =IFERROR(SUMIFS($E117:$Q117,$E$5:$Q$5,">="&U$4,$E$5:$Q$5,"<="&U$5),0)*U$2 -> 1670908
B118: TC Rent | C118: Rent Revenue - TC | F118: =+SUMIFS(F$25:F$113,$B$25:$B$113,$C118) -> 0 | G118: =+SUMIFS(G$25:G$113,$B$25:$B$113,$C118) -> 0 | H118: =+SUMIFS(H$25:H$113,$B$25:$B$113,$C118) -> 0 | I118: =+SUMIFS(I$25:I$113,$B$25:$B$113,$C118) -> 0 | J118: =+SUMIFS(J$25:J$113,$B$25:$B$113,$C118) -> 0 | K118: =+SUMIFS(K$25:K$113,$B$25:$B$113,$C118) -> 0 | L118: =+SUMIFS(L$25:L$113,$B$25:$B$113,$C118) -> 0 | M118: =+SUMIFS(M$25:M$113,$B$25:$B$113,$C118) -> 0 | ... Q118: =+SUMIFS(Q$25:Q$113,$B$25:$B$113,$C118) -> 0 | S118: =IFERROR(SUMIFS($E118:$Q118,$E$5:$Q$5,">="&S$4,$E$5:$Q$5,"<="&S$5),0)*S$2 -> 0 | T118: =IFERROR(SUMIFS($E118:$Q118,$E$5:$Q$5,">="&T$4,$E$5:$Q$5,"<="&T$5),0)*T$2 -> 0 | U118: =IFERROR(SUMIFS($E118:$Q118,$E$5:$Q$5,">="&U$4,$E$5:$Q$5,"<="&U$5),0)*U$2 -> 0
B119: MC Rent | C119: Rent Revenue - MC | F119: =+SUMIFS(F$25:F$113,$B$25:$B$113,$C119) -> 86707 | G119: =+SUMIFS(G$25:G$113,$B$25:$B$113,$C119) -> 93912 | H119: =+SUMIFS(H$25:H$113,$B$25:$B$113,$C119) -> 93135 | I119: =+SUMIFS(I$25:I$113,$B$25:$B$113,$C119) -> 92846 | J119: =+SUMIFS(J$25:J$113,$B$25:$B$113,$C119) -> 101036 | K119: =+SUMIFS(K$25:K$113,$B$25:$B$113,$C119) -> 94072 | L119: =+SUMIFS(L$25:L$113,$B$25:$B$113,$C119) -> 94660 | M119: =+SUMIFS(M$25:M$113,$B$25:$B$113,$C119) -> 102463 | ... Q119: =+SUMIFS(Q$25:Q$113,$B$25:$B$113,$C119) -> 101595 | S119: =IFERROR(SUMIFS($E119:$Q119,$E$5:$Q$5,">="&S$4,$E$5:$Q$5,"<="&S$5),0)*S$2 -> 1155856 | T119: =IFERROR(SUMIFS($E119:$Q119,$E$5:$Q$5,">="&T$4,$E$5:$Q$5,"<="&T$5),0)*T$2 -> 1188296 | U119: =IFERROR(SUMIFS($E119:$Q119,$E$5:$Q$5,">="&U$4,$E$5:$Q$5,"<="&U$5),0)*U$2 -> 1181216
B120: Rent Concessions | C120: Rent Concessions | F120: =+SUMIFS(F$25:F$113,$B$25:$B$113,$C120) -> 0 | G120: =+SUMIFS(G$25:G$113,$B$25:$B$113,$C120) -> 0 | H120: =+SUMIFS(H$25:H$113,$B$25:$B$113,$C120) -> 0 | I120: =+SUMIFS(I$25:I$113,$B$25:$B$113,$C120) -> 0 | J120: =+SUMIFS(J$25:J$113,$B$25:$B$113,$C120) -> 0 | K120: =+SUMIFS(K$25:K$113,$B$25:$B$113,$C120) -> 0 | L120: =+SUMIFS(L$25:L$113,$B$25:$B$113,$C120) -> 0 | M120: =+SUMIFS(M$25:M$113,$B$25:$B$113,$C120) -> 0 | ... Q120: =+SUMIFS(Q$25:Q$113,$B$25:$B$113,$C120) -> 0 | S120: =IFERROR(SUMIFS($E120:$Q120,$E$5:$Q$5,">="&S$4,$E$5:$Q$5,"<="&S$5),0)*S$2 -> 0 | T120: =IFERROR(SUMIFS($E120:$Q120,$E$5:$Q$5,">="&T$4,$E$5:$Q$5,"<="&T$5),0)*T$2 -> 0 | U120: =IFERROR(SUMIFS($E120:$Q120,$E$5:$Q$5,">="&U$4,$E$5:$Q$5,"<="&U$5),0)*U$2 -> 0
B121: Other Revenue | C121: Other Revenue | F121: =+SUMIFS(F$25:F$113,$B$25:$B$113,$C121) -> 6094 | G121: =+SUMIFS(G$25:G$113,$B$25:$B$113,$C121) -> 5169 | H121: =+SUMIFS(H$25:H$113,$B$25:$B$113,$C121) -> 5035 | I121: =+SUMIFS(I$25:I$113,$B$25:$B$113,$C121) -> 5675 | J121: =+SUMIFS(J$25:J$113,$B$25:$B$113,$C121) -> 5730 | K121: =+SUMIFS(K$25:K$113,$B$25:$B$113,$C121) -> 5439 | L121: =+SUMIFS(L$25:L$113,$B$25:$B$113,$C121) -> 5568 | M121: =+SUMIFS(M$25:M$113,$B$25:$B$113,$C121) -> 5520 | ... Q121: =+SUMIFS(Q$25:Q$113,$B$25:$B$113,$C121) -> 5659 | S121: =IFERROR(SUMIFS($E121:$Q121,$E$5:$Q$5,">="&S$4,$E$5:$Q$5,"<="&S$5),0)*S$2 -> 66566 | T121: =IFERROR(SUMIFS($E121:$Q121,$E$5:$Q$5,">="&T$4,$E$5:$Q$5,"<="&T$5),0)*T$2 -> 66848 | U121: =IFERROR(SUMIFS($E121:$Q121,$E$5:$Q$5,">="&U$4,$E$5:$Q$5,"<="&U$5),0)*U$2 -> 68820
B122: Other Revenue | C122: Commercial Lease Revenue | F122: =+SUMIFS(F$25:F$113,$B$25:$B$113,$C122) -> 0 | G122: =+SUMIFS(G$25:G$113,$B$25:$B$113,$C122) -> 0 | H122: =+SUMIFS(H$25:H$113,$B$25:$B$113,$C122) -> 0 | I122: =+SUMIFS(I$25:I$113,$B$25:$B$113,$C122) -> 0 | J122: =+SUMIFS(J$25:J$113,$B$25:$B$113,$C122) -> 0 | K122: =+SUMIFS(K$25:K$113,$B$25:$B$113,$C122) -> 0 | L122: =+SUMIFS(L$25:L$113,$B$25:$B$113,$C122) -> 0 | M122: =+SUMIFS(M$25:M$113,$B$25:$B$113,$C122) -> 0 | ... Q122: =+SUMIFS(Q$25:Q$113,$B$25:$B$113,$C122) -> 0 | S122: =IFERROR(SUMIFS($E122:$Q122,$E$5:$Q$5,">="&S$4,$E$5:$Q$5,"<="&S$5),0)*S$2 -> 0 | T122: =IFERROR(SUMIFS($E122:$Q122,$E$5:$Q$5,">="&T$4,$E$5:$Q$5,"<="&T$5),0)*T$2 -> 0 | U122: =IFERROR(SUMIFS($E122:$Q122,$E$5:$Q$5,">="&U$4,$E$5:$Q$5,"<="&U$5),0)*U$2 -> 0
B123: Other Revenue | C123: Rent - Second Person | F123: =+SUMIFS(F$25:F$113,$B$25:$B$113,$C123) -> 7297 | G123: =+SUMIFS(G$25:G$113,$B$25:$B$113,$C123) -> 7396 | H123: =+SUMIFS(H$25:H$113,$B$25:$B$113,$C123) -> 7551 | I123: =+SUMIFS(I$25:I$113,$B$25:$B$113,$C123) -> 7493 | J123: =+SUMIFS(J$25:J$113,$B$25:$B$113,$C123) -> 7787 | K123: =+SUMIFS(K$25:K$113,$B$25:$B$113,$C123) -> 7905 | L123: =+SUMIFS(L$25:L$113,$B$25:$B$113,$C123) -> 7847 | M123: =+SUMIFS(M$25:M$113,$B$25:$B$113,$C123) -> 7539 | ... Q123: =+SUMIFS(Q$25:Q$113,$B$25:$B$113,$C123) -> 7960 | S123: =IFERROR(SUMIFS($E123:$Q123,$E$5:$Q$5,">="&S$4,$E$5:$Q$5,"<="&S$5),0)*S$2 -> 92194 | T123: =IFERROR(SUMIFS($E123:$Q123,$E$5:$Q$5,">="&T$4,$E$5:$Q$5,"<="&T$5),0)*T$2 -> 93530 | U123: =IFERROR(SUMIFS($E123:$Q123,$E$5:$Q$5,">="&U$4,$E$5:$Q$5,"<="&U$5),0)*U$2 -> 94964
B124: AL Care | C124: Care Revenue - AL | F124: =+SUMIFS(F$25:F$113,$B$25:$B$113,$C124) -> 25794 | G124: =+SUMIFS(G$25:G$113,$B$25:$B$113,$C124) -> 26554 | H124: =+SUMIFS(H$25:H$113,$B$25:$B$113,$C124) -> 26411 | I124: =+SUMIFS(I$25:I$113,$B$25:$B$113,$C124) -> 25486 | J124: =+SUMIFS(J$25:J$113,$B$25:$B$113,$C124) -> 26677 | K124: =+SUMIFS(K$25:K$113,$B$25:$B$113,$C124) -> 27880 | L124: =+SUMIFS(L$25:L$113,$B$25:$B$113,$C124) -> 27928 | M124: =+SUMIFS(M$25:M$113,$B$25:$B$113,$C124) -> 26782 | ... Q124: =+SUMIFS(Q$25:Q$113,$B$25:$B$113,$C124) -> 27660 | S124: =IFERROR(SUMIFS($E124:$Q124,$E$5:$Q$5,">="&S$4,$E$5:$Q$5,"<="&S$5),0)*S$2 -> 322560 | T124: =IFERROR(SUMIFS($E124:$Q124,$E$5:$Q$5,">="&T$4,$E$5:$Q$5,"<="&T$5),0)*T$2 -> 327516 | U124: =IFERROR(SUMIFS($E124:$Q124,$E$5:$Q$5,">="&U$4,$E$5:$Q$5,"<="&U$5),0)*U$2 -> 329992
B125: MC Care | C125: Care Revenue - MC | F125: =+SUMIFS(F$25:F$113,$B$25:$B$113,$C125) -> 15207 | G125: =+SUMIFS(G$25:G$113,$B$25:$B$113,$C125) -> 16471 | H125: =+SUMIFS(H$25:H$113,$B$25:$B$113,$C125) -> 16462 | I125: =+SUMIFS(I$25:I$113,$B$25:$B$113,$C125) -> 16569 | J125: =+SUMIFS(J$25:J$113,$B$25:$B$113,$C125) -> 18104 | K125: =+SUMIFS(K$25:K$113,$B$25:$B$113,$C125) -> 16781 | L125: =+SUMIFS(L$25:L$113,$B$25:$B$113,$C125) -> 16726 | M125: =+SUMIFS(M$25:M$113,$B$25:$B$113,$C125) -> 17969 | ... Q125: =+SUMIFS(Q$25:Q$113,$B$25:$B$113,$C125) -> 18000 | S125: =IFERROR(SUMIFS($E125:$Q125,$E$5:$Q$5,">="&S$4,$E$5:$Q$5,"<="&S$5),0)*S$2 -> 204547 | T125: =IFERROR(SUMIFS($E125:$Q125,$E$5:$Q$5,">="&T$4,$E$5:$Q$5,"<="&T$5),0)*T$2 -> 209906 | U125: =IFERROR(SUMIFS($E125:$Q125,$E$5:$Q$5,">="&U$4,$E$5:$Q$5,"<="&U$5),0)*U$2 -> 209664
B126: Community Fees | C126: Community Fees | F126: =+SUMIFS(F$25:F$113,$B$25:$B$113,$C126) -> 4087 | G126: =+SUMIFS(G$25:G$113,$B$25:$B$113,$C126) -> 9901 | H126: =+SUMIFS(H$25:H$113,$B$25:$B$113,$C126) -> 5616 | I126: =+SUMIFS(I$25:I$113,$B$25:$B$113,$C126) -> 3000 | J126: =+SUMIFS(J$25:J$113,$B$25:$B$113,$C126) -> 13391 | K126: =+SUMIFS(K$25:K$113,$B$25:$B$113,$C126) -> 3969 | L126: =+SUMIFS(L$25:L$113,$B$25:$B$113,$C126) -> 3000 | M126: =+SUMIFS(M$25:M$113,$B$25:$B$113,$C126) -> 3000 | ... Q126: =+SUMIFS(Q$25:Q$113,$B$25:$B$113,$C126) -> 3000 | S126: =IFERROR(SUMIFS($E126:$Q126,$E$5:$Q$5,">="&S$4,$E$5:$Q$5,"<="&S$5),0)*S$2 -> 69359 | T126: =IFERROR(SUMIFS($E126:$Q126,$E$5:$Q$5,">="&T$4,$E$5:$Q$5,"<="&T$5),0)*T$2 -> 58790 | U126: =IFERROR(SUMIFS($E126:$Q126,$E$5:$Q$5,">="&U$4,$E$5:$Q$5,"<="&U$5),0)*U$2 -> 67860
C127: Total Revenue | F127: =+SUM(F116:F126) -> 396248 | G127: =+SUM(G116:G126) -> 414961 | H127: =+SUM(H116:H126) -> 411841 | I127: =+SUM(I116:I126) -> 402092 | J127: =+SUM(J116:J126) -> 431295 | K127: =+SUM(K116:K126) -> 420291 | L127: =+SUM(L116:L126) -> 422160 | M127: =+SUM(M116:M126) -> 422829 | ... Q127: =+SUM(Q116:Q126) -> 433334 | S127: =+SUM(S116:S126) -> 5041509 | T127: =+SUM(T116:T126) -> 5129562 | U127: =+SUM(U116:U126) -> 5165088
B129: Check | F129: =F127-'AR Historical Financials'!E26 -> 0 | G129: =G127-'AR Historical Financials'!F26 -> 0 | H129: =H127-'AR Historical Financials'!G26 -> 0 | I129: =I127-'AR Historical Financials'!H26 -> 0 | J129: =J127-'AR Historical Financials'!I26 -> 0 | K129: =K127-'AR Historical Financials'!J26 -> 0 | L129: =L127-'AR Historical Financials'!K26 -> 0 | M129: =M127-'AR Historical Financials'!L26 -> 0 | ... Q129: =Q127-'AR Historical Financials'!P26 -> 0 | S129: =S127-'AR Historical Financials'!Q26 -> 0
B131: Culinary | C131: Wages - Culinary | F131: =+SUMIFS(F$25:F$113,$B$25:$B$113,$C131) -> 29572 | G131: =+SUMIFS(G$25:G$113,$B$25:$B$113,$C131) -> 29295 | H131: =+SUMIFS(H$25:H$113,$B$25:$B$113,$C131) -> 29378 | I131: =+SUMIFS(I$25:I$113,$B$25:$B$113,$C131) -> 29730 | J131: =+SUMIFS(J$25:J$113,$B$25:$B$113,$C131) -> 29967 | K131: =+SUMIFS(K$25:K$113,$B$25:$B$113,$C131) -> 29829 | L131: =+SUMIFS(L$25:L$113,$B$25:$B$113,$C131) -> 29467 | M131: =+SUMIFS(M$25:M$113,$B$25:$B$113,$C131) -> 29277 | ... Q131: =+SUMIFS(Q$25:Q$113,$B$25:$B$113,$C131) -> 29731 | S131: =IFERROR(SUMIFS($E131:$Q131,$E$5:$Q$5,">="&S$4,$E$5:$Q$5,"<="&S$5),0)*S$2 -> 355506 | T131: =IFERROR(SUMIFS($E131:$Q131,$E$5:$Q$5,">="&T$4,$E$5:$Q$5,"<="&T$5),0)*T$2 -> 355470 | U131: =IFERROR(SUMIFS($E131:$Q131,$E$5:$Q$5,">="&U$4,$E$5:$Q$5,"<="&U$5),0)*U$2 -> 358100
B132: Activities | C132: Wages - Activities | F132: =+SUMIFS(F$25:F$113,$B$25:$B$113,$C132) -> 6209 | G132: =+SUMIFS(G$25:G$113,$B$25:$B$113,$C132) -> 6286 | H132: =+SUMIFS(H$25:H$113,$B$25:$B$113,$C132) -> 6331 | I132: =+SUMIFS(I$25:I$113,$B$25:$B$113,$C132) -> 6294 | J132: =+SUMIFS(J$25:J$113,$B$25:$B$113,$C132) -> 6215 | K132: =+SUMIFS(K$25:K$113,$B$25:$B$113,$C132) -> 6181 | L132: =+SUMIFS(L$25:L$113,$B$25:$B$113,$C132) -> 6229 | M132: =+SUMIFS(M$25:M$113,$B$25:$B$113,$C132) -> 6306 | ... Q132: =+SUMIFS(Q$25:Q$113,$B$25:$B$113,$C132) -> 6187 | S132: =IFERROR(SUMIFS($E132:$Q132,$E$5:$Q$5,">="&S$4,$E$5:$Q$5,"<="&S$5),0)*S$2 -> 75035 | T132: =IFERROR(SUMIFS($E132:$Q132,$E$5:$Q$5,">="&T$4,$E$5:$Q$5,"<="&T$5),0)*T$2 -> 75038 | U132: =IFERROR(SUMIFS($E132:$Q132,$E$5:$Q$5,">="&U$4,$E$5:$Q$5,"<="&U$5),0)*U$2 -> 74624
B133: Direct Care | C133: Wages - Direct Care | F133: =+SUMIFS(F$25:F$113,$B$25:$B$113,$C133) -> 68373 | G133: =+SUMIFS(G$25:G$113,$B$25:$B$113,$C133) -> 67917 | H133: =+SUMIFS(H$25:H$113,$B$25:$B$113,$C133) -> 67137 | I133: =+SUMIFS(I$25:I$113,$B$25:$B$113,$C133) -> 66884 | J133: =+SUMIFS(J$25:J$113,$B$25:$B$113,$C133) -> 67437 | K133: =+SUMIFS(K$25:K$113,$B$25:$B$113,$C133) -> 68189 | L133: =+SUMIFS(L$25:L$113,$B$25:$B$113,$C133) -> 68320 | M133: =+SUMIFS(M$25:M$113,$B$25:$B$113,$C133) -> 67686 | ... Q133: =+SUMIFS(Q$25:Q$113,$B$25:$B$113,$C133) -> 68315 | S133: =IFERROR(SUMIFS($E133:$Q133,$E$5:$Q$5,">="&S$4,$E$5:$Q$5,"<="&S$5),0)*S$2 -> 811885 | T133: =IFERROR(SUMIFS($E133:$Q133,$E$5:$Q$5,">="&T$4,$E$5:$Q$5,"<="&T$5),0)*T$2 -> 811896 | U133: =IFERROR(SUMIFS($E133:$Q133,$E$5:$Q$5,">="&U$4,$E$5:$Q$5,"<="&U$5),0)*U$2 -> 811848
B134: Maintenance | C134: Wages - Maintenance | F134: =+SUMIFS(F$25:F$113,$B$25:$B$113,$C134) -> 8912 | G134: =+SUMIFS(G$25:G$113,$B$25:$B$113,$C134) -> 8996 | H134: =+SUMIFS(H$25:H$113,$B$25:$B$113,$C134) -> 9102 | I134: =+SUMIFS(I$25:I$113,$B$25:$B$113,$C134) -> 9114 | J134: =+SUMIFS(J$25:J$113,$B$25:$B$113,$C134) -> 9019 | K134: =+SUMIFS(K$25:K$113,$B$25:$B$113,$C134) -> 8921 | L134: =+SUMIFS(L$25:L$113,$B$25:$B$113,$C134) -> 8927 | M134: =+SUMIFS(M$25:M$113,$B$25:$B$113,$C134) -> 9030 | ... Q134: =+SUMIFS(Q$25:Q$113,$B$25:$B$113,$C134) -> 8910 | S134: =IFERROR(SUMIFS($E134:$Q134,$E$5:$Q$5,">="&S$4,$E$5:$Q$5,"<="&S$5),0)*S$2 -> 108128 | T134: =IFERROR(SUMIFS($E134:$Q134,$E$5:$Q$5,">="&T$4,$E$5:$Q$5,"<="&T$5),0)*T$2 -> 108128 | U134: =IFERROR(SUMIFS($E134:$Q134,$E$5:$Q$5,">="&U$4,$E$5:$Q$5,"<="&U$5),0)*U$2 -> 107956
B135: Housekeeping | C135: Wages - Housekeeping | F135: =+SUMIFS(F$25:F$113,$B$25:$B$113,$C135) -> 12278 | G135: =+SUMIFS(G$25:G$113,$B$25:$B$113,$C135) -> 12315 | H135: =+SUMIFS(H$25:H$113,$B$25:$B$113,$C135) -> 12466 | I135: =+SUMIFS(I$25:I$113,$B$25:$B$113,$C135) -> 12567 | J135: =+SUMIFS(J$25:J$113,$B$25:$B$113,$C135) -> 12507 | K135: =+SUMIFS(K$25:K$113,$B$25:$B$113,$C135) -> 12352 | L135: =+SUMIFS(L$25:L$113,$B$25:$B$113,$C135) -> 12271 | M135: =+SUMIFS(M$25:M$113,$B$25:$B$113,$C135) -> 12353 | ... Q135: =+SUMIFS(Q$25:Q$113,$B$25:$B$113,$C135) -> 12314 | S135: =IFERROR(SUMIFS($E135:$Q135,$E$5:$Q$5,">="&S$4,$E$5:$Q$5,"<="&S$5),0)*S$2 -> 148963 | T135: =IFERROR(SUMIFS($E135:$Q135,$E$5:$Q$5,">="&T$4,$E$5:$Q$5,"<="&T$5),0)*T$2 -> 148956 | U135: =IFERROR(SUMIFS($E135:$Q135,$E$5:$Q$5,">="&U$4,$E$5:$Q$5,"<="&U$5),0)*U$2 -> 149384
B136: Marketing | C136: Wages - Marketing | F136: =+SUMIFS(F$25:F$113,$B$25:$B$113,$C136) -> 7075 | G136: =+SUMIFS(G$25:G$113,$B$25:$B$113,$C136) -> 7019 | H136: =+SUMIFS(H$25:H$113,$B$25:$B$113,$C136) -> 6933 | I136: =+SUMIFS(I$25:I$113,$B$25:$B$113,$C136) -> 6912 | J136: =+SUMIFS(J$25:J$113,$B$25:$B$113,$C136) -> 6978 | K136: =+SUMIFS(K$25:K$113,$B$25:$B$113,$C136) -> 7059 | L136: =+SUMIFS(L$25:L$113,$B$25:$B$113,$C136) -> 7067 | M136: =+SUMIFS(M$25:M$113,$B$25:$B$113,$C136) -> 6993 | ... Q136: =+SUMIFS(Q$25:Q$113,$B$25:$B$113,$C136) -> 7072 | S136: =IFERROR(SUMIFS($E136:$Q136,$E$5:$Q$5,">="&S$4,$E$5:$Q$5,"<="&S$5),0)*S$2 -> 83955 | T136: =IFERROR(SUMIFS($E136:$Q136,$E$5:$Q$5,">="&T$4,$E$5:$Q$5,"<="&T$5),0)*T$2 -> 83958 | U136: =IFERROR(SUMIFS($E136:$Q136,$E$5:$Q$5,">="&U$4,$E$5:$Q$5,"<="&U$5),0)*U$2 -> 84004
B137: Admin | C137: Wages - Admin | F137: =+SUMIFS(F$25:F$113,$B$25:$B$113,$C137) -> 21274 | G137: =+SUMIFS(G$25:G$113,$B$25:$B$113,$C137) -> 21380 | H137: =+SUMIFS(H$25:H$113,$B$25:$B$113,$C137) -> 21244 | I137: =+SUMIFS(I$25:I$113,$B$25:$B$113,$C137) -> 21017 | J137: =+SUMIFS(J$25:J$113,$B$25:$B$113,$C137) -> 20945 | K137: =+SUMIFS(K$25:K$113,$B$25:$B$113,$C137) -> 21108 | L137: =+SUMIFS(L$25:L$113,$B$25:$B$113,$C137) -> 21328 | M137: =+SUMIFS(M$25:M$113,$B$25:$B$113,$C137) -> 21364 | ... Q137: =+SUMIFS(Q$25:Q$113,$B$25:$B$113,$C137) -> 21178 | S137: =IFERROR(SUMIFS($E137:$Q137,$E$5:$Q$5,">="&S$4,$E$5:$Q$5,"<="&S$5),0)*S$2 -> 253959 | T137: =IFERROR(SUMIFS($E137:$Q137,$E$5:$Q$5,">="&T$4,$E$5:$Q$5,"<="&T$5),0)*T$2 -> 253982 | U137: =IFERROR(SUMIFS($E137:$Q137,$E$5:$Q$5,">="&U$4,$E$5:$Q$5,"<="&U$5),0)*U$2 -> 252484
B138: Marketing | C138: Bonuses - Marketing | F138: =+SUMIFS(F$25:F$113,$B$25:$B$113,$C138) -> 0 | G138: =+SUMIFS(G$25:G$113,$B$25:$B$113,$C138) -> 0 | H138: =+SUMIFS(H$25:H$113,$B$25:$B$113,$C138) -> 0 | I138: =+SUMIFS(I$25:I$113,$B$25:$B$113,$C138) -> 0 | J138: =+SUMIFS(J$25:J$113,$B$25:$B$113,$C138) -> 0 | K138: =+SUMIFS(K$25:K$113,$B$25:$B$113,$C138) -> 0 | L138: =+SUMIFS(L$25:L$113,$B$25:$B$113,$C138) -> 0 | M138: =+SUMIFS(M$25:M$113,$B$25:$B$113,$C138) -> 0 | ... Q138: =+SUMIFS(Q$25:Q$113,$B$25:$B$113,$C138) -> 0 | S138: =IFERROR(SUMIFS($E138:$Q138,$E$5:$Q$5,">="&S$4,$E$5:$Q$5,"<="&S$5),0)*S$2 -> 0 | T138: =IFERROR(SUMIFS($E138:$Q138,$E$5:$Q$5,">="&T$4,$E$5:$Q$5,"<="&T$5),0)*T$2 -> 0 | U138: =IFERROR(SUMIFS($E138:$Q138,$E$5:$Q$5,">="&U$4,$E$5:$Q$5,"<="&U$5),0)*U$2 -> 0
B139: Admin | C139: Bonuses - Admin | F139: =+SUMIFS(F$25:F$113,$B$25:$B$113,$C139) -> 0 | G139: =+SUMIFS(G$25:G$113,$B$25:$B$113,$C139) -> 0 | H139: =+SUMIFS(H$25:H$113,$B$25:$B$113,$C139) -> 0 | I139: =+SUMIFS(I$25:I$113,$B$25:$B$113,$C139) -> 0 | J139: =+SUMIFS(J$25:J$113,$B$25:$B$113,$C139) -> 0 | K139: =+SUMIFS(K$25:K$113,$B$25:$B$113,$C139) -> 0 | L139: =+SUMIFS(L$25:L$113,$B$25:$B$113,$C139) -> 0 | M139: =+SUMIFS(M$25:M$113,$B$25:$B$113,$C139) -> 0 | ... Q139: =+SUMIFS(Q$25:Q$113,$B$25:$B$113,$C139) -> 0 | S139: =IFERROR(SUMIFS($E139:$Q139,$E$5:$Q$5,">="&S$4,$E$5:$Q$5,"<="&S$5),0)*S$2 -> 0 | T139: =IFERROR(SUMIFS($E139:$Q139,$E$5:$Q$5,">="&T$4,$E$5:$Q$5,"<="&T$5),0)*T$2 -> 0 | U139: =IFERROR(SUMIFS($E139:$Q139,$E$5:$Q$5,">="&U$4,$E$5:$Q$5,"<="&U$5),0)*U$2 -> 0
C140: In-House Labor | F140: =+SUM(F131:F139) -> 153693 | G140: =+SUM(G131:G139) -> 153208 | H140: =+SUM(H131:H139) -> 152591 | I140: =+SUM(I131:I139) -> 152518 | J140: =+SUM(J131:J139) -> 153068 | K140: =+SUM(K131:K139) -> 153639 | L140: =+SUM(L131:L139) -> 153609 | M140: =+SUM(M131:M139) -> 153009 | ... Q140: =+SUM(Q131:Q139) -> 153707 | S140: =+SUM(S131:S139) -> 1837431 | T140: =+SUM(T131:T139) -> 1837428 | U140: =+SUM(U131:U139) -> 1838400
B142: Culinary | C142: Contract Labor - Culinary | F142: =+SUMIFS(F$25:F$113,$B$25:$B$113,$C142) -> 0 | G142: =+SUMIFS(G$25:G$113,$B$25:$B$113,$C142) -> 0 | H142: =+SUMIFS(H$25:H$113,$B$25:$B$113,$C142) -> 0 | I142: =+SUMIFS(I$25:I$113,$B$25:$B$113,$C142) -> 0 | J142: =+SUMIFS(J$25:J$113,$B$25:$B$113,$C142) -> 0 | K142: =+SUMIFS(K$25:K$113,$B$25:$B$113,$C142) -> 0 | L142: =+SUMIFS(L$25:L$113,$B$25:$B$113,$C142) -> 0 | M142: =+SUMIFS(M$25:M$113,$B$25:$B$113,$C142) -> 0 | ... Q142: =+SUMIFS(Q$25:Q$113,$B$25:$B$113,$C142) -> 0 | S142: =IFERROR(SUMIFS($E142:$Q142,$E$5:$Q$5,">="&S$4,$E$5:$Q$5,"<="&S$5),0)*S$2 -> 0 | T142: =IFERROR(SUMIFS($E142:$Q142,$E$5:$Q$5,">="&T$4,$E$5:$Q$5,"<="&T$5),0)*T$2 -> 0 | U142: =IFERROR(SUMIFS($E142:$Q142,$E$5:$Q$5,">="&U$4,$E$5:$Q$5,"<="&U$5),0)*U$2 -> 0
B143: Activities | C143: Contract Labor - Activities | F143: =+SUMIFS(F$25:F$113,$B$25:$B$113,$C143) -> 0 | G143: =+SUMIFS(G$25:G$113,$B$25:$B$113,$C143) -> 0 | H143: =+SUMIFS(H$25:H$113,$B$25:$B$113,$C143) -> 0 | I143: =+SUMIFS(I$25:I$113,$B$25:$B$113,$C143) -> 0 | J143: =+SUMIFS(J$25:J$113,$B$25:$B$113,$C143) -> 0 | K143: =+SUMIFS(K$25:K$113,$B$25:$B$113,$C143) -> 0 | L143: =+SUMIFS(L$25:L$113,$B$25:$B$113,$C143) -> 0 | M143: =+SUMIFS(M$25:M$113,$B$25:$B$113,$C143) -> 0 | ... Q143: =+SUMIFS(Q$25:Q$113,$B$25:$B$113,$C143) -> 0 | S143: =IFERROR(SUMIFS($E143:$Q143,$E$5:$Q$5,">="&S$4,$E$5:$Q$5,"<="&S$5),0)*S$2 -> 0 | T143: =IFERROR(SUMIFS($E143:$Q143,$E$5:$Q$5,">="&T$4,$E$5:$Q$5,"<="&T$5),0)*T$2 -> 0 | U143: =IFERROR(SUMIFS($E143:$Q143,$E$5:$Q$5,">="&U$4,$E$5:$Q$5,"<="&U$5),0)*U$2 -> 0
B144: Direct Care | C144: Contract Labor - Direct Care | F144: =+SUMIFS(F$25:F$113,$B$25:$B$113,$C144) -> 0 | G144: =+SUMIFS(G$25:G$113,$B$25:$B$113,$C144) -> 0 | H144: =+SUMIFS(H$25:H$113,$B$25:$B$113,$C144) -> 0 | I144: =+SUMIFS(I$25:I$113,$B$25:$B$113,$C144) -> 0 | J144: =+SUMIFS(J$25:J$113,$B$25:$B$113,$C144) -> 0 | K144: =+SUMIFS(K$25:K$113,$B$25:$B$113,$C144) -> 0 | L144: =+SUMIFS(L$25:L$113,$B$25:$B$113,$C144) -> 0 | M144: =+SUMIFS(M$25:M$113,$B$25:$B$113,$C144) -> 0 | ... Q144: =+SUMIFS(Q$25:Q$113,$B$25:$B$113,$C144) -> 0 | S144: =IFERROR(SUMIFS($E144:$Q144,$E$5:$Q$5,">="&S$4,$E$5:$Q$5,"<="&S$5),0)*S$2 -> 0 | T144: =IFERROR(SUMIFS($E144:$Q144,$E$5:$Q$5,">="&T$4,$E$5:$Q$5,"<="&T$5),0)*T$2 -> 0 | U144: =IFERROR(SUMIFS($E144:$Q144,$E$5:$Q$5,">="&U$4,$E$5:$Q$5,"<="&U$5),0)*U$2 -> 0
B145: Maintenance | C145: Contract Labor - Maintenance | F145: =+SUMIFS(F$25:F$113,$B$25:$B$113,$C145) -> 0 | G145: =+SUMIFS(G$25:G$113,$B$25:$B$113,$C145) -> 0 | H145: =+SUMIFS(H$25:H$113,$B$25:$B$113,$C145) -> 0 | I145: =+SUMIFS(I$25:I$113,$B$25:$B$113,$C145) -> 0 | J145: =+SUMIFS(J$25:J$113,$B$25:$B$113,$C145) -> 0 | K145: =+SUMIFS(K$25:K$113,$B$25:$B$113,$C145) -> 0 | L145: =+SUMIFS(L$25:L$113,$B$25:$B$113,$C145) -> 0 | M145: =+SUMIFS(M$25:M$113,$B$25:$B$113,$C145) -> 0 | ... Q145: =+SUMIFS(Q$25:Q$113,$B$25:$B$113,$C145) -> 0 | S145: =IFERROR(SUMIFS($E145:$Q145,$E$5:$Q$5,">="&S$4,$E$5:$Q$5,"<="&S$5),0)*S$2 -> 0 | T145: =IFERROR(SUMIFS($E145:$Q145,$E$5:$Q$5,">="&T$4,$E$5:$Q$5,"<="&T$5),0)*T$2 -> 0 | U145: =IFERROR(SUMIFS($E145:$Q145,$E$5:$Q$5,">="&U$4,$E$5:$Q$5,"<="&U$5),0)*U$2 -> 0
B146: Housekeeping | C146: Contract Labor - Housekeeping | F146: =+SUMIFS(F$25:F$113,$B$25:$B$113,$C146) -> 0 | G146: =+SUMIFS(G$25:G$113,$B$25:$B$113,$C146) -> 0 | H146: =+SUMIFS(H$25:H$113,$B$25:$B$113,$C146) -> 0 | I146: =+SUMIFS(I$25:I$113,$B$25:$B$113,$C146) -> 0 | J146: =+SUMIFS(J$25:J$113,$B$25:$B$113,$C146) -> 0 | K146: =+SUMIFS(K$25:K$113,$B$25:$B$113,$C146) -> 0 | L146: =+SUMIFS(L$25:L$113,$B$25:$B$113,$C146) -> 0 | M146: =+SUMIFS(M$25:M$113,$B$25:$B$113,$C146) -> 0 | ... Q146: =+SUMIFS(Q$25:Q$113,$B$25:$B$113,$C146) -> 0 | S146: =IFERROR(SUMIFS($E146:$Q146,$E$5:$Q$5,">="&S$4,$E$5:$Q$5,"<="&S$5),0)*S$2 -> 0 | T146: =IFERROR(SUMIFS($E146:$Q146,$E$5:$Q$5,">="&T$4,$E$5:$Q$5,"<="&T$5),0)*T$2 -> 0 | U146: =IFERROR(SUMIFS($E146:$Q146,$E$5:$Q$5,">="&U$4,$E$5:$Q$5,"<="&U$5),0)*U$2 -> 0
B147: Marketing | C147: Contract Labor - Marketing | F147: =+SUMIFS(F$25:F$113,$B$25:$B$113,$C147) -> 0 | G147: =+SUMIFS(G$25:G$113,$B$25:$B$113,$C147) -> 0 | H147: =+SUMIFS(H$25:H$113,$B$25:$B$113,$C147) -> 0 | I147: =+SUMIFS(I$25:I$113,$B$25:$B$113,$C147) -> 0 | J147: =+SUMIFS(J$25:J$113,$B$25:$B$113,$C147) -> 0 | K147: =+SUMIFS(K$25:K$113,$B$25:$B$113,$C147) -> 0 | L147: =+SUMIFS(L$25:L$113,$B$25:$B$113,$C147) -> 0 | M147: =+SUMIFS(M$25:M$113,$B$25:$B$113,$C147) -> 0 | ... Q147: =+SUMIFS(Q$25:Q$113,$B$25:$B$113,$C147) -> 0 | S147: =IFERROR(SUMIFS($E147:$Q147,$E$5:$Q$5,">="&S$4,$E$5:$Q$5,"<="&S$5),0)*S$2 -> 0 | T147: =IFERROR(SUMIFS($E147:$Q147,$E$5:$Q$5,">="&T$4,$E$5:$Q$5,"<="&T$5),0)*T$2 -> 0 | U147: =IFERROR(SUMIFS($E147:$Q147,$E$5:$Q$5,">="&U$4,$E$5:$Q$5,"<="&U$5),0)*U$2 -> 0
B148: Admin | C148: Contract Labor - Admin | F148: =+SUMIFS(F$25:F$113,$B$25:$B$113,$C148) -> 0 | G148: =+SUMIFS(G$25:G$113,$B$25:$B$113,$C148) -> 0 | H148: =+SUMIFS(H$25:H$113,$B$25:$B$113,$C148) -> 0 | I148: =+SUMIFS(I$25:I$113,$B$25:$B$113,$C148) -> 0 | J148: =+SUMIFS(J$25:J$113,$B$25:$B$113,$C148) -> 0 | K148: =+SUMIFS(K$25:K$113,$B$25:$B$113,$C148) -> 0 | L148: =+SUMIFS(L$25:L$113,$B$25:$B$113,$C148) -> 0 | M148: =+SUMIFS(M$25:M$113,$B$25:$B$113,$C148) -> 0 | ... Q148: =+SUMIFS(Q$25:Q$113,$B$25:$B$113,$C148) -> 0 | S148: =IFERROR(SUMIFS($E148:$Q148,$E$5:$Q$5,">="&S$4,$E$5:$Q$5,"<="&S$5),0)*S$2 -> 0 | T148: =IFERROR(SUMIFS($E148:$Q148,$E$5:$Q$5,">="&T$4,$E$5:$Q$5,"<="&T$5),0)*T$2 -> 0 | U148: =IFERROR(SUMIFS($E148:$Q148,$E$5:$Q$5,">="&U$4,$E$5:$Q$5,"<="&U$5),0)*U$2 -> 0
C149: Total Labor | F149: =+SUM(F140:F148) -> 153693 | G149: =+SUM(G140:G148) -> 153208 | H149: =+SUM(H140:H148) -> 152591 | I149: =+SUM(I140:I148) -> 152518 | J149: =+SUM(J140:J148) -> 153068 | K149: =+SUM(K140:K148) -> 153639 | L149: =+SUM(L140:L148) -> 153609 | M149: =+SUM(M140:M148) -> 153009 | ... Q149: =+SUM(Q140:Q148) -> 153707 | S149: =+SUM(S140:S148) -> 1837431 | T149: =+SUM(T140:T148) -> 1837428 | U149: =+SUM(U140:U148) -> 1838400
B151: Culinary | C151: Benefits - Culinary | F151: =+SUMIFS(F$25:F$113,$B$25:$B$113,$C151) -> 0 | G151: =+SUMIFS(G$25:G$113,$B$25:$B$113,$C151) -> 0 | H151: =+SUMIFS(H$25:H$113,$B$25:$B$113,$C151) -> 0 | I151: =+SUMIFS(I$25:I$113,$B$25:$B$113,$C151) -> 0 | J151: =+SUMIFS(J$25:J$113,$B$25:$B$113,$C151) -> 0 | K151: =+SUMIFS(K$25:K$113,$B$25:$B$113,$C151) -> 0 | L151: =+SUMIFS(L$25:L$113,$B$25:$B$113,$C151) -> 0 | M151: =+SUMIFS(M$25:M$113,$B$25:$B$113,$C151) -> 0 | ... Q151: =+SUMIFS(Q$25:Q$113,$B$25:$B$113,$C151) -> 0 | S151: =IFERROR(SUMIFS($E151:$Q151,$E$5:$Q$5,">="&S$4,$E$5:$Q$5,"<="&S$5),0)*S$2 -> 0 | T151: =IFERROR(SUMIFS($E151:$Q151,$E$5:$Q$5,">="&T$4,$E$5:$Q$5,"<="&T$5),0)*T$2 -> 0 | U151: =IFERROR(SUMIFS($E151:$Q151,$E$5:$Q$5,">="&U$4,$E$5:$Q$5,"<="&U$5),0)*U$2 -> 0
B152: Activities | C152: Benefits - Activities | F152: =+SUMIFS(F$25:F$113,$B$25:$B$113,$C152) -> 0 | G152: =+SUMIFS(G$25:G$113,$B$25:$B$113,$C152) -> 0 | H152: =+SUMIFS(H$25:H$113,$B$25:$B$113,$C152) -> 0 | I152: =+SUMIFS(I$25:I$113,$B$25:$B$113,$C152) -> 0 | J152: =+SUMIFS(J$25:J$113,$B$25:$B$113,$C152) -> 0 | K152: =+SUMIFS(K$25:K$113,$B$25:$B$113,$C152) -> 0 | L152: =+SUMIFS(L$25:L$113,$B$25:$B$113,$C152) -> 0 | M152: =+SUMIFS(M$25:M$113,$B$25:$B$113,$C152) -> 0 | ... Q152: =+SUMIFS(Q$25:Q$113,$B$25:$B$113,$C152) -> 0 | S152: =IFERROR(SUMIFS($E152:$Q152,$E$5:$Q$5,">="&S$4,$E$5:$Q$5,"<="&S$5),0)*S$2 -> 0 | T152: =IFERROR(SUMIFS($E152:$Q152,$E$5:$Q$5,">="&T$4,$E$5:$Q$5,"<="&T$5),0)*T$2 -> 0 | U152: =IFERROR(SUMIFS($E152:$Q152,$E$5:$Q$5,">="&U$4,$E$5:$Q$5,"<="&U$5),0)*U$2 -> 0
B153: Direct Care | C153: Benefits - Direct Care | F153: =+SUMIFS(F$25:F$113,$B$25:$B$113,$C153) -> 0 | G153: =+SUMIFS(G$25:G$113,$B$25:$B$113,$C153) -> 0 | H153: =+SUMIFS(H$25:H$113,$B$25:$B$113,$C153) -> 0 | I153: =+SUMIFS(I$25:I$113,$B$25:$B$113,$C153) -> 0 | J153: =+SUMIFS(J$25:J$113,$B$25:$B$113,$C153) -> 0 | K153: =+SUMIFS(K$25:K$113,$B$25:$B$113,$C153) -> 0 | L153: =+SUMIFS(L$25:L$113,$B$25:$B$113,$C153) -> 0 | M153: =+SUMIFS(M$25:M$113,$B$25:$B$113,$C153) -> 0 | ... Q153: =+SUMIFS(Q$25:Q$113,$B$25:$B$113,$C153) -> 0 | S153: =IFERROR(SUMIFS($E153:$Q153,$E$5:$Q$5,">="&S$4,$E$5:$Q$5,"<="&S$5),0)*S$2 -> 0 | T153: =IFERROR(SUMIFS($E153:$Q153,$E$5:$Q$5,">="&T$4,$E$5:$Q$5,"<="&T$5),0)*T$2 -> 0 | U153: =IFERROR(SUMIFS($E153:$Q153,$E$5:$Q$5,">="&U$4,$E$5:$Q$5,"<="&U$5),0)*U$2 -> 0
B154: Maintenance | C154: Benefits - Maintenance | F154: =+SUMIFS(F$25:F$113,$B$25:$B$113,$C154) -> 0 | G154: =+SUMIFS(G$25:G$113,$B$25:$B$113,$C154) -> 0 | H154: =+SUMIFS(H$25:H$113,$B$25:$B$113,$C154) -> 0 | I154: =+SUMIFS(I$25:I$113,$B$25:$B$113,$C154) -> 0 | J154: =+SUMIFS(J$25:J$113,$B$25:$B$113,$C154) -> 0 | K154: =+SUMIFS(K$25:K$113,$B$25:$B$113,$C154) -> 0 | L154: =+SUMIFS(L$25:L$113,$B$25:$B$113,$C154) -> 0 | M154: =+SUMIFS(M$25:M$113,$B$25:$B$113,$C154) -> 0 | ... Q154: =+SUMIFS(Q$25:Q$113,$B$25:$B$113,$C154) -> 0 | S154: =IFERROR(SUMIFS($E154:$Q154,$E$5:$Q$5,">="&S$4,$E$5:$Q$5,"<="&S$5),0)*S$2 -> 0 | T154: =IFERROR(SUMIFS($E154:$Q154,$E$5:$Q$5,">="&T$4,$E$5:$Q$5,"<="&T$5),0)*T$2 -> 0 | U154: =IFERROR(SUMIFS($E154:$Q154,$E$5:$Q$5,">="&U$4,$E$5:$Q$5,"<="&U$5),0)*U$2 -> 0
B155: Housekeeping | C155: Benefits - Housekeeping | F155: =+SUMIFS(F$25:F$113,$B$25:$B$113,$C155) -> 0 | G155: =+SUMIFS(G$25:G$113,$B$25:$B$113,$C155) -> 0 | H155: =+SUMIFS(H$25:H$113,$B$25:$B$113,$C155) -> 0 | I155: =+SUMIFS(I$25:I$113,$B$25:$B$113,$C155) -> 0 | J155: =+SUMIFS(J$25:J$113,$B$25:$B$113,$C155) -> 0 | K155: =+SUMIFS(K$25:K$113,$B$25:$B$113,$C155) -> 0 | L155: =+SUMIFS(L$25:L$113,$B$25:$B$113,$C155) -> 0 | M155: =+SUMIFS(M$25:M$113,$B$25:$B$113,$C155) -> 0 | ... Q155: =+SUMIFS(Q$25:Q$113,$B$25:$B$113,$C155) -> 0 | S155: =IFERROR(SUMIFS($E155:$Q155,$E$5:$Q$5,">="&S$4,$E$5:$Q$5,"<="&S$5),0)*S$2 -> 0 | T155: =IFERROR(SUMIFS($E155:$Q155,$E$5:$Q$5,">="&T$4,$E$5:$Q$5,"<="&T$5),0)*T$2 -> 0 | U155: =IFERROR(SUMIFS($E155:$Q155,$E$5:$Q$5,">="&U$4,$E$5:$Q$5,"<="&U$5),0)*U$2 -> 0
B156: Marketing | C156: Benefits - Marketing | F156: =+SUMIFS(F$25:F$113,$B$25:$B$113,$C156) -> 0 | G156: =+SUMIFS(G$25:G$113,$B$25:$B$113,$C156) -> 0 | H156: =+SUMIFS(H$25:H$113,$B$25:$B$113,$C156) -> 0 | I156: =+SUMIFS(I$25:I$113,$B$25:$B$113,$C156) -> 0 | J156: =+SUMIFS(J$25:J$113,$B$25:$B$113,$C156) -> 0 | K156: =+SUMIFS(K$25:K$113,$B$25:$B$113,$C156) -> 0 | L156: =+SUMIFS(L$25:L$113,$B$25:$B$113,$C156) -> 0 | M156: =+SUMIFS(M$25:M$113,$B$25:$B$113,$C156) -> 0 | ... Q156: =+SUMIFS(Q$25:Q$113,$B$25:$B$113,$C156) -> 0 | S156: =IFERROR(SUMIFS($E156:$Q156,$E$5:$Q$5,">="&S$4,$E$5:$Q$5,"<="&S$5),0)*S$2 -> 0 | T156: =IFERROR(SUMIFS($E156:$Q156,$E$5:$Q$5,">="&T$4,$E$5:$Q$5,"<="&T$5),0)*T$2 -> 0 | U156: =IFERROR(SUMIFS($E156:$Q156,$E$5:$Q$5,">="&U$4,$E$5:$Q$5,"<="&U$5),0)*U$2 -> 0
B157: Admin | C157: Benefits - Admin | F157: =+SUMIFS(F$25:F$113,$B$25:$B$113,$C157) -> 25897 | G157: =+SUMIFS(G$25:G$113,$B$25:$B$113,$C157) -> 25890 | H157: =+SUMIFS(H$25:H$113,$B$25:$B$113,$C157) -> 25817 | I157: =+SUMIFS(I$25:I$113,$B$25:$B$113,$C157) -> 25751 | J157: =+SUMIFS(J$25:J$113,$B$25:$B$113,$C157) -> 25726 | K157: =+SUMIFS(K$25:K$113,$B$25:$B$113,$C157) -> 25722 | L157: =+SUMIFS(L$25:L$113,$B$25:$B$113,$C157) -> 25707 | M157: =+SUMIFS(M$25:M$113,$B$25:$B$113,$C157) -> 25689 | ... Q157: =+SUMIFS(Q$25:Q$113,$B$25:$B$113,$C157) -> 25922 | S157: =IFERROR(SUMIFS($E157:$Q157,$E$5:$Q$5,">="&S$4,$E$5:$Q$5,"<="&S$5),0)*S$2 -> 309527 | T157: =IFERROR(SUMIFS($E157:$Q157,$E$5:$Q$5,">="&T$4,$E$5:$Q$5,"<="&T$5),0)*T$2 -> 309448 | U157: =IFERROR(SUMIFS($E157:$Q157,$E$5:$Q$5,">="&U$4,$E$5:$Q$5,"<="&U$5),0)*U$2 -> 310460
C158: Total Labor & Benefits | F158: =+SUM(F149:F157) -> 179590 | G158: =+SUM(G149:G157) -> 179098 | H158: =+SUM(H149:H157) -> 178408 | I158: =+SUM(I149:I157) -> 178269 | J158: =+SUM(J149:J157) -> 178794 | K158: =+SUM(K149:K157) -> 179361 | L158: =+SUM(L149:L157) -> 179316 | M158: =+SUM(M149:M157) -> 178698 | ... Q158: =+SUM(Q149:Q157) -> 179629 | S158: =+SUM(S149:S157) -> 2146958 | T158: =+SUM(T149:T157) -> 2146876 | U158: =+SUM(U149:U157) -> 2148860
B160: Culinary | C160: Culinary | F160: =+SUMIFS(F$25:F$113,$B$25:$B$113,$C160) -> 2252 | G160: =+SUMIFS(G$25:G$113,$B$25:$B$113,$C160) -> 2234 | H160: =+SUMIFS(H$25:H$113,$B$25:$B$113,$C160) -> 2193 | I160: =+SUMIFS(I$25:I$113,$B$25:$B$113,$C160) -> 2165 | J160: =+SUMIFS(J$25:J$113,$B$25:$B$113,$C160) -> 2177 | K160: =+SUMIFS(K$25:K$113,$B$25:$B$113,$C160) -> 2217 | L160: =+SUMIFS(L$25:L$113,$B$25:$B$113,$C160) -> 2249 | M160: =+SUMIFS(M$25:M$113,$B$25:$B$113,$C160) -> 2243 | ... Q160: =+SUMIFS(Q$25:Q$113,$B$25:$B$113,$C160) -> 2205 | S160: =IFERROR(SUMIFS($E160:$Q160,$E$5:$Q$5,">="&S$4,$E$5:$Q$5,"<="&S$5),0)*S$2 -> 26478 | T160: =IFERROR(SUMIFS($E160:$Q160,$E$5:$Q$5,">="&T$4,$E$5:$Q$5,"<="&T$5),0)*T$2 -> 26480 | U160: =IFERROR(SUMIFS($E160:$Q160,$E$5:$Q$5,">="&U$4,$E$5:$Q$5,"<="&U$5),0)*U$2 -> 26172
B161: Culinary | C161: Raw Food | F161: =+SUMIFS(F$25:F$113,$B$25:$B$113,$C161) -> 14219 | G161: =+SUMIFS(G$25:G$113,$B$25:$B$113,$C161) -> 14256 | H161: =+SUMIFS(H$25:H$113,$B$25:$B$113,$C161) -> 14128 | I161: =+SUMIFS(I$25:I$113,$B$25:$B$113,$C161) -> 13913 | J161: =+SUMIFS(J$25:J$113,$B$25:$B$113,$C161) -> 13740 | K161: =+SUMIFS(K$25:K$113,$B$25:$B$113,$C161) -> 13716 | L161: =+SUMIFS(L$25:L$113,$B$25:$B$113,$C161) -> 13854 | M161: =+SUMIFS(M$25:M$113,$B$25:$B$113,$C161) -> 14071 | ... Q161: =+SUMIFS(Q$25:Q$113,$B$25:$B$113,$C161) -> 13882 | S161: =IFERROR(SUMIFS($E161:$Q161,$E$5:$Q$5,">="&S$4,$E$5:$Q$5,"<="&S$5),0)*S$2 -> 168360 | T161: =IFERROR(SUMIFS($E161:$Q161,$E$5:$Q$5,">="&T$4,$E$5:$Q$5,"<="&T$5),0)*T$2 -> 168776 | U161: =IFERROR(SUMIFS($E161:$Q161,$E$5:$Q$5,">="&U$4,$E$5:$Q$5,"<="&U$5),0)*U$2 -> 168912
B162: Activities | C162: Activities | F162: =+SUMIFS(F$25:F$113,$B$25:$B$113,$C162) -> 0 | G162: =+SUMIFS(G$25:G$113,$B$25:$B$113,$C162) -> 0 | H162: =+SUMIFS(H$25:H$113,$B$25:$B$113,$C162) -> 0 | I162: =+SUMIFS(I$25:I$113,$B$25:$B$113,$C162) -> 0 | J162: =+SUMIFS(J$25:J$113,$B$25:$B$113,$C162) -> 0 | K162: =+SUMIFS(K$25:K$113,$B$25:$B$113,$C162) -> 0 | L162: =+SUMIFS(L$25:L$113,$B$25:$B$113,$C162) -> 0 | M162: =+SUMIFS(M$25:M$113,$B$25:$B$113,$C162) -> 0 | ... Q162: =+SUMIFS(Q$25:Q$113,$B$25:$B$113,$C162) -> 0 | S162: =IFERROR(SUMIFS($E162:$Q162,$E$5:$Q$5,">="&S$4,$E$5:$Q$5,"<="&S$5),0)*S$2 -> 0 | T162: =IFERROR(SUMIFS($E162:$Q162,$E$5:$Q$5,">="&T$4,$E$5:$Q$5,"<="&T$5),0)*T$2 -> 0 | U162: =IFERROR(SUMIFS($E162:$Q162,$E$5:$Q$5,">="&U$4,$E$5:$Q$5,"<="&U$5),0)*U$2 -> 0
B163: Direct Care | C163: Direct Care | F163: =+SUMIFS(F$25:F$113,$B$25:$B$113,$C163) -> 3340 | G163: =+SUMIFS(G$25:G$113,$B$25:$B$113,$C163) -> 3258 | H163: =+SUMIFS(H$25:H$113,$B$25:$B$113,$C163) -> 3265 | I163: =+SUMIFS(I$25:I$113,$B$25:$B$113,$C163) -> 3350 | J163: =+SUMIFS(J$25:J$113,$B$25:$B$113,$C163) -> 3372 | K163: =+SUMIFS(K$25:K$113,$B$25:$B$113,$C163) -> 3294 | L163: =+SUMIFS(L$25:L$113,$B$25:$B$113,$C163) -> 3246 | M163: =+SUMIFS(M$25:M$113,$B$25:$B$113,$C163) -> 3308 | ... Q163: =+SUMIFS(Q$25:Q$113,$B$25:$B$113,$C163) -> 3267 | S163: =IFERROR(SUMIFS($E163:$Q163,$E$5:$Q$5,">="&S$4,$E$5:$Q$5,"<="&S$5),0)*S$2 -> 39671 | T163: =IFERROR(SUMIFS($E163:$Q163,$E$5:$Q$5,">="&T$4,$E$5:$Q$5,"<="&T$5),0)*T$2 -> 39584 | U163: =IFERROR(SUMIFS($E163:$Q163,$E$5:$Q$5,">="&U$4,$E$5:$Q$5,"<="&U$5),0)*U$2 -> 39448
B164: Non-Departmental | C164: COGS | F164: =+SUMIFS(F$25:F$113,$B$25:$B$113,$C164) -> 0 | G164: =+SUMIFS(G$25:G$113,$B$25:$B$113,$C164) -> 0 | H164: =+SUMIFS(H$25:H$113,$B$25:$B$113,$C164) -> 0 | I164: =+SUMIFS(I$25:I$113,$B$25:$B$113,$C164) -> 0 | J164: =+SUMIFS(J$25:J$113,$B$25:$B$113,$C164) -> 0 | K164: =+SUMIFS(K$25:K$113,$B$25:$B$113,$C164) -> 0 | L164: =+SUMIFS(L$25:L$113,$B$25:$B$113,$C164) -> 0 | M164: =+SUMIFS(M$25:M$113,$B$25:$B$113,$C164) -> 0 | ... Q164: =+SUMIFS(Q$25:Q$113,$B$25:$B$113,$C164) -> 0 | S164: =IFERROR(SUMIFS($E164:$Q164,$E$5:$Q$5,">="&S$4,$E$5:$Q$5,"<="&S$5),0)*S$2 -> 0 | T164: =IFERROR(SUMIFS($E164:$Q164,$E$5:$Q$5,">="&T$4,$E$5:$Q$5,"<="&T$5),0)*T$2 -> 0 | U164: =IFERROR(SUMIFS($E164:$Q164,$E$5:$Q$5,">="&U$4,$E$5:$Q$5,"<="&U$5),0)*U$2 -> 0
B165: Maintenance | C165: Maintenance | F165: =+SUMIFS(F$25:F$113,$B$25:$B$113,$C165) -> 6661 | G165: =+SUMIFS(G$25:G$113,$B$25:$B$113,$C165) -> 6442 | H165: =+SUMIFS(H$25:H$113,$B$25:$B$113,$C165) -> 6360 | I165: =+SUMIFS(I$25:I$113,$B$25:$B$113,$C165) -> 6478 | J165: =+SUMIFS(J$25:J$113,$B$25:$B$113,$C165) -> 6707 | K165: =+SUMIFS(K$25:K$113,$B$25:$B$113,$C165) -> 6873 | L165: =+SUMIFS(L$25:L$113,$B$25:$B$113,$C165) -> 6850 | M165: =+SUMIFS(M$25:M$113,$B$25:$B$113,$C165) -> 6657 | ... Q165: =+SUMIFS(Q$25:Q$113,$B$25:$B$113,$C165) -> 6711 | S165: =IFERROR(SUMIFS($E165:$Q165,$E$5:$Q$5,">="&S$4,$E$5:$Q$5,"<="&S$5),0)*S$2 -> 79020 | T165: =IFERROR(SUMIFS($E165:$Q165,$E$5:$Q$5,">="&T$4,$E$5:$Q$5,"<="&T$5),0)*T$2 -> 78998 | U165: =IFERROR(SUMIFS($E165:$Q165,$E$5:$Q$5,">="&U$4,$E$5:$Q$5,"<="&U$5),0)*U$2 -> 78212
B166: Utilities | C166: Utilities | F166: =+SUMIFS(F$25:F$113,$B$25:$B$113,$C166) -> 18855 | G166: =+SUMIFS(G$25:G$113,$B$25:$B$113,$C166) -> 19338 | H166: =+SUMIFS(H$25:H$113,$B$25:$B$113,$C166) -> 17397 | I166: =+SUMIFS(I$25:I$113,$B$25:$B$113,$C166) -> 16818 | J166: =+SUMIFS(J$25:J$113,$B$25:$B$113,$C166) -> 18037 | K166: =+SUMIFS(K$25:K$113,$B$25:$B$113,$C166) -> 20535 | L166: =+SUMIFS(L$25:L$113,$B$25:$B$113,$C166) -> 21676 | M166: =+SUMIFS(M$25:M$113,$B$25:$B$113,$C166) -> 20843 | ... Q166: =+SUMIFS(Q$25:Q$113,$B$25:$B$113,$C166) -> 18064 | S166: =IFERROR(SUMIFS($E166:$Q166,$E$5:$Q$5,">="&S$4,$E$5:$Q$5,"<="&S$5),0)*S$2 -> 222545 | T166: =IFERROR(SUMIFS($E166:$Q166,$E$5:$Q$5,">="&T$4,$E$5:$Q$5,"<="&T$5),0)*T$2 -> 223130 | U166: =IFERROR(SUMIFS($E166:$Q166,$E$5:$Q$5,">="&U$4,$E$5:$Q$5,"<="&U$5),0)*U$2 -> 202088
B167: Housekeeping | C167: Housekeeping | F167: =+SUMIFS(F$25:F$113,$B$25:$B$113,$C167) -> 2620 | G167: =+SUMIFS(G$25:G$113,$B$25:$B$113,$C167) -> 2568 | H167: =+SUMIFS(H$25:H$113,$B$25:$B$113,$C167) -> 2526 | I167: =+SUMIFS(I$25:I$113,$B$25:$B$113,$C167) -> 2548 | J167: =+SUMIFS(J$25:J$113,$B$25:$B$113,$C167) -> 2606 | K167: =+SUMIFS(K$25:K$113,$B$25:$B$113,$C167) -> 2626 | L167: =+SUMIFS(L$25:L$113,$B$25:$B$113,$C167) -> 2582 | M167: =+SUMIFS(M$25:M$113,$B$25:$B$113,$C167) -> 2531 | ... Q167: =+SUMIFS(Q$25:Q$113,$B$25:$B$113,$C167) -> 2596 | S167: =IFERROR(SUMIFS($E167:$Q167,$E$5:$Q$5,">="&S$4,$E$5:$Q$5,"<="&S$5),0)*S$2 -> 30960 | T167: =IFERROR(SUMIFS($E167:$Q167,$E$5:$Q$5,">="&T$4,$E$5:$Q$5,"<="&T$5),0)*T$2 -> 30932 | U167: =IFERROR(SUMIFS($E167:$Q167,$E$5:$Q$5,">="&U$4,$E$5:$Q$5,"<="&U$5),0)*U$2 -> 31264
B168: Marketing | C168: Marketing | F168: =+SUMIFS(F$25:F$113,$B$25:$B$113,$C168) -> 5535 | G168: =+SUMIFS(G$25:G$113,$B$25:$B$113,$C168) -> 5400 | H168: =+SUMIFS(H$25:H$113,$B$25:$B$113,$C168) -> 5242 | I168: =+SUMIFS(I$25:I$113,$B$25:$B$113,$C168) -> 5118 | J168: =+SUMIFS(J$25:J$113,$B$25:$B$113,$C168) -> 5069 | K168: =+SUMIFS(K$25:K$113,$B$25:$B$113,$C168) -> 5114 | L168: =+SUMIFS(L$25:L$113,$B$25:$B$113,$C168) -> 5236 | M168: =+SUMIFS(M$25:M$113,$B$25:$B$113,$C168) -> 5393 | ... Q168: =+SUMIFS(Q$25:Q$113,$B$25:$B$113,$C168) -> 5470 | S168: =IFERROR(SUMIFS($E168:$Q168,$E$5:$Q$5,">="&S$4,$E$5:$Q$5,"<="&S$5),0)*S$2 -> 64284 | T168: =IFERROR(SUMIFS($E168:$Q168,$E$5:$Q$5,">="&T$4,$E$5:$Q$5,"<="&T$5),0)*T$2 -> 65612 | U168: =IFERROR(SUMIFS($E168:$Q168,$E$5:$Q$5,">="&U$4,$E$5:$Q$5,"<="&U$5),0)*U$2 -> 66588
B169: Marketing | C169: Marketing - Contract Services | F169: =+SUMIFS(F$25:F$113,$B$25:$B$113,$C169) -> 0 | G169: =+SUMIFS(G$25:G$113,$B$25:$B$113,$C169) -> 0 | H169: =+SUMIFS(H$25:H$113,$B$25:$B$113,$C169) -> 0 | I169: =+SUMIFS(I$25:I$113,$B$25:$B$113,$C169) -> 0 | J169: =+SUMIFS(J$25:J$113,$B$25:$B$113,$C169) -> 0 | K169: =+SUMIFS(K$25:K$113,$B$25:$B$113,$C169) -> 0 | L169: =+SUMIFS(L$25:L$113,$B$25:$B$113,$C169) -> 0 | M169: =+SUMIFS(M$25:M$113,$B$25:$B$113,$C169) -> 0 | ... Q169: =+SUMIFS(Q$25:Q$113,$B$25:$B$113,$C169) -> 0 | S169: =IFERROR(SUMIFS($E169:$Q169,$E$5:$Q$5,">="&S$4,$E$5:$Q$5,"<="&S$5),0)*S$2 -> 0 | T169: =IFERROR(SUMIFS($E169:$Q169,$E$5:$Q$5,">="&T$4,$E$5:$Q$5,"<="&T$5),0)*T$2 -> 0 | U169: =IFERROR(SUMIFS($E169:$Q169,$E$5:$Q$5,">="&U$4,$E$5:$Q$5,"<="&U$5),0)*U$2 -> 0
B170: Marketing | C170: Marketing - Referral Fees | F170: =+SUMIFS(F$25:F$113,$B$25:$B$113,$C170) -> 0 | G170: =+SUMIFS(G$25:G$113,$B$25:$B$113,$C170) -> 0 | H170: =+SUMIFS(H$25:H$113,$B$25:$B$113,$C170) -> 0 | I170: =+SUMIFS(I$25:I$113,$B$25:$B$113,$C170) -> 0 | J170: =+SUMIFS(J$25:J$113,$B$25:$B$113,$C170) -> 0 | K170: =+SUMIFS(K$25:K$113,$B$25:$B$113,$C170) -> 0 | L170: =+SUMIFS(L$25:L$113,$B$25:$B$113,$C170) -> 0 | M170: =+SUMIFS(M$25:M$113,$B$25:$B$113,$C170) -> 0 | ... Q170: =+SUMIFS(Q$25:Q$113,$B$25:$B$113,$C170) -> 0 | S170: =IFERROR(SUMIFS($E170:$Q170,$E$5:$Q$5,">="&S$4,$E$5:$Q$5,"<="&S$5),0)*S$2 -> 0 | T170: =IFERROR(SUMIFS($E170:$Q170,$E$5:$Q$5,">="&T$4,$E$5:$Q$5,"<="&T$5),0)*T$2 -> 0 | U170: =IFERROR(SUMIFS($E170:$Q170,$E$5:$Q$5,">="&U$4,$E$5:$Q$5,"<="&U$5),0)*U$2 -> 0
B171: Admin | C171: Admin | F171: =+SUMIFS(F$25:F$113,$B$25:$B$113,$C171) -> 4128 | G171: =+SUMIFS(G$25:G$113,$B$25:$B$113,$C171) -> 4162 | H171: =+SUMIFS(H$25:H$113,$B$25:$B$113,$C171) -> 4340 | I171: =+SUMIFS(I$25:I$113,$B$25:$B$113,$C171) -> 4296 | J171: =+SUMIFS(J$25:J$113,$B$25:$B$113,$C171) -> 4120 | K171: =+SUMIFS(K$25:K$113,$B$25:$B$113,$C171) -> 4175 | L171: =+SUMIFS(L$25:L$113,$B$25:$B$113,$C171) -> 4347 | M171: =+SUMIFS(M$25:M$113,$B$25:$B$113,$C171) -> 4282 | ... Q171: =+SUMIFS(Q$25:Q$113,$B$25:$B$113,$C171) -> 4268 | S171: =IFERROR(SUMIFS($E171:$Q171,$E$5:$Q$5,">="&S$4,$E$5:$Q$5,"<="&S$5),0)*S$2 -> 50774 | T171: =IFERROR(SUMIFS($E171:$Q171,$E$5:$Q$5,">="&T$4,$E$5:$Q$5,"<="&T$5),0)*T$2 -> 51106 | U171: =IFERROR(SUMIFS($E171:$Q171,$E$5:$Q$5,">="&U$4,$E$5:$Q$5,"<="&U$5),0)*U$2 -> 51240
... B186: Non-Departmental | C186: Other Taxes | F186: =+SUMIFS(F$25:F$113,$B$25:$B$113,$C186) -> 0 | G186: =+SUMIFS(G$25:G$113,$B$25:$B$113,$C186) -> 0 | H186: =+SUMIFS(H$25:H$113,$B$25:$B$113,$C186) -> 0 | I186: =+SUMIFS(I$25:I$113,$B$25:$B$113,$C186) -> 0 | J186: =+SUMIFS(J$25:J$113,$B$25:$B$113,$C186) -> 0 | K186: =+SUMIFS(K$25:K$113,$B$25:$B$113,$C186) -> 0 | L186: =+SUMIFS(L$25:L$113,$B$25:$B$113,$C186) -> 0 | M186: =+SUMIFS(M$25:M$113,$B$25:$B$113,$C186) -> 0 | ... Q186: =+SUMIFS(Q$25:Q$113,$B$25:$B$113,$C186) -> 0 | S186: =IFERROR(SUMIFS($E186:$Q186,$E$5:$Q$5,">="&S$4,$E$5:$Q$5,"<="&S$5),0)*S$2 -> 0 | T186: =IFERROR(SUMIFS($E186:$Q186,$E$5:$Q$5,">="&T$4,$E$5:$Q$5,"<="&T$5),0)*T$2 -> 0 | U186: =IFERROR(SUMIFS($E186:$Q186,$E$5:$Q$5,">="&U$4,$E$5:$Q$5,"<="&U$5),0)*U$2 -> 0
C187: Total Opex | F187: =+SUM(F158:F186) -> 266011 | G187: =+SUM(G158:G186) -> 265578 | H187: =+SUM(H158:H186) -> 262685 | I187: =+SUM(I158:I186) -> 261779 | J187: =+SUM(J158:J186) -> 263436 | K187: =+SUM(K158:K186) -> 266711 | L187: =+SUM(L158:L186) -> 268141 | M187: =+SUM(M158:M186) -> 266799 | ... Q187: =+SUM(Q158:Q186) -> 264880 | S187: =+SUM(S158:S186) -> 3174601 | T187: =+SUM(T158:T186) -> 3176802 | U187: =+SUM(U158:U186) -> 3158104
C189: EBITDARM | F189: =+F127-F187 -> 130237 | G189: =+G127-G187 -> 149383 | H189: =+H127-H187 -> 149156 | I189: =+I127-I187 -> 140313 | J189: =+J127-J187 -> 167859 | K189: =+K127-K187 -> 153580 | L189: =+L127-L187 -> 154019 | M189: =+M127-M187 -> 156030 | ... Q189: =+Q127-Q187 -> 168454 | S189: =+S127-S187 -> 1866908 | T189: =+T127-T187 -> 1952760 | U189: =+U127-U187 -> 2006984
B190: Management Fee | C190: Management Fee | F190: =+SUMIFS(F$25:F$113,$B$25:$B$113,$C190) -> 19812 | G190: =+SUMIFS(G$25:G$113,$B$25:$B$113,$C190) -> 20748 | H190: =+SUMIFS(H$25:H$113,$B$25:$B$113,$C190) -> 20592 | I190: =+SUMIFS(I$25:I$113,$B$25:$B$113,$C190) -> 20105 | J190: =+SUMIFS(J$25:J$113,$B$25:$B$113,$C190) -> 21565 | K190: =+SUMIFS(K$25:K$113,$B$25:$B$113,$C190) -> 21015 | L190: =+SUMIFS(L$25:L$113,$B$25:$B$113,$C190) -> 21108 | M190: =+SUMIFS(M$25:M$113,$B$25:$B$113,$C190) -> 21141 | ... Q190: =+SUMIFS(Q$25:Q$113,$B$25:$B$113,$C190) -> 21667 | S190: =IFERROR(SUMIFS($E190:$Q190,$E$5:$Q$5,">="&S$4,$E$5:$Q$5,"<="&S$5),0)*S$2 -> 252076 | T190: =IFERROR(SUMIFS($E190:$Q190,$E$5:$Q$5,">="&T$4,$E$5:$Q$5,"<="&T$5),0)*T$2 -> 256478 | U190: =IFERROR(SUMIFS($E190:$Q190,$E$5:$Q$5,">="&U$4,$E$5:$Q$5,"<="&U$5),0)*U$2 -> 258256
C191: EBITDAR | F191: =+F189-F190 -> 110425 | G191: =+G189-G190 -> 128635 | H191: =+H189-H190 -> 128564 | I191: =+I189-I190 -> 120208 | J191: =+J189-J190 -> 146294 | K191: =+K189-K190 -> 132565 | L191: =+L189-L190 -> 132911 | M191: =+M189-M190 -> 134889 | ... Q191: =+Q189-Q190 -> 146787 | S191: =+S189-S190 -> 1614832 | T191: =+T189-T190 -> 1696282 | U191: =+U189-U190 -> 1748728
C192: Margin | F192: =+F191/F127 -> 0.27867649 | G192: =+G191/G127 -> 0.30999299 | H192: =+H191/H127 -> 0.31216902 | I192: =+I191/I127 -> 0.29895646 | J192: =+J191/J127 -> 0.33919707 | K192: =+K191/K127 -> 0.31541242 | L192: =+L191/L127 -> 0.31483561 | M192: =+M191/M127 -> 0.31901549 | ... Q192: =+Q191/Q127 -> 0.33873871 | S192: =+S191/S127 -> 0.32030727 | T192: =+T191/T127 -> 0.33068749 | U192: =+U191/U127 -> 0.33856693
B193: Ignore | C193: Ignore
B195: Check | F195: =F191-'AR Historical Financials'!E92 -> 0 | G195: =G191-'AR Historical Financials'!F92 -> 0 | H195: =H191-'AR Historical Financials'!G92 -> 0 | I195: =I191-'AR Historical Financials'!H92 -> 0 | J195: =J191-'AR Historical Financials'!I92 -> 0 | K195: =K191-'AR Historical Financials'!J92 -> 0 | L195: =L191-'AR Historical Financials'!K92 -> 0 | M195: =M191-'AR Historical Financials'!L92 -> 0 | ... Q195: =Q191-'AR Historical Financials'!P92 -> 0 | S195: =S191-'AR Historical Financials'!Q92 -> 0
B197: Units | F197: =+F12 -> 84 | G197: =+G12 -> 84 | H197: =+H12 -> 84 | I197: =+I12 -> 84 | J197: =+J12 -> 84 | K197: =+K12 -> 84 | L197: =+L12 -> 84 | M197: =+M12 -> 84 | ... Q197: =+Q12 -> 84 | S197: =+S12 -> 84 | T197: =+T12 -> 84 | U197: =+U12 -> 84
B198: Occupied Units | F198: =+F17 -> 71 | G198: =+G17 -> 73 | H198: =+H17 -> 74 | I198: =+I17 -> 73 | J198: =+J17 -> 76 | K198: =+K17 -> 76 | L198: =+L17 -> 76 | M198: =+M17 -> 75 | ... Q198: =+Q17 -> 78 | S198: =+S17 -> 75.166667 | T198: =+T17 -> 76.5 | U198: =+U17 -> 77.333333
B199: Residents/Occupied Units | F199: 1 | G199: =+F199 -> 1 | H199: =+G199 -> 1 | I199: =+H199 -> 1 | J199: =+I199 -> 1 | K199: =+J199 -> 1 | L199: =+K199 -> 1 | M199: =+L199 -> 1 | N199: =+M199 -> 1 | ... Q199: =+P199 -> 1 | S199: =$F$199 -> 1 | T199: =$F$199 -> 1 | U199: =$F$199 -> 1
B200: Resident Days | F200: =+F24 -> 2201 | G200: =+G24 -> 2263 | H200: =+H24 -> 2220 | I200: =+I24 -> 2263 | J200: =+J24 -> 2280 | K200: =+K24 -> 2356 | L200: =+L24 -> 2356 | M200: =+M24 -> 2100 | ... Q200: =+Q24 -> 2340 | S200: =+S24 -> 27433 | T200: =+T24 -> 27700 | U200: =+U24 -> 28152
B201: Total Labor | F201: =+F149 -> 153693 | G201: =+G149 -> 153208 | H201: =+H149 -> 152591 | I201: =+I149 -> 152518 | J201: =+J149 -> 153068 | K201: =+K149 -> 153639 | L201: =+L149 -> 153609 | M201: =+M149 -> 153009 | ... Q201: =+Q149 -> 153707 | S201: =+S149 -> 1837431 | T201: =+T149 -> 1837428 | U201: =+U149 -> 1838400
B202: Total Benefits | F202: =+SUM(F151:F157) -> 25897 | G202: =+SUM(G151:G157) -> 25890 | H202: =+SUM(H151:H157) -> 25817 | I202: =+SUM(I151:I157) -> 25751 | J202: =+SUM(J151:J157) -> 25726 | K202: =+SUM(K151:K157) -> 25722 | L202: =+SUM(L151:L157) -> 25707 | M202: =+SUM(M151:M157) -> 25689 | ... Q202: =+SUM(Q151:Q157) -> 25922 | S202: =+SUM(S151:S157) -> 309527 | T202: =+SUM(T151:T157) -> 309448 | U202: =+SUM(U151:U157) -> 310460
B203: Total Revenue | F203: =+F127 -> 396248 | G203: =+G127 -> 414961 | H203: =+H127 -> 411841 | I203: =+I127 -> 402092 | J203: =+J127 -> 431295 | K203: =+K127 -> 420291 | L203: =+L127 -> 422160 | M203: =+M127 -> 422829 | ... Q203: =+Q127 -> 433334 | S203: =+S127 -> 5041509 | T203: =+T127 -> 5129562 | U203: =+U127 -> 5165088
B205: Bonuses - Marketing | C205: $ Unit | D205: Bonuses - Marketing | F205: =+SUMIFS(F$116:F$186,$C$116:$C$186,$D205)/F$197 -> 0 | G205: =+SUMIFS(G$116:G$186,$C$116:$C$186,$D205)/G$197 -> 0 | H205: =+SUMIFS(H$116:H$186,$C$116:$C$186,$D205)/H$197 -> 0 | I205: =+SUMIFS(I$116:I$186,$C$116:$C$186,$D205)/I$197 -> 0 | J205: =+SUMIFS(J$116:J$186,$C$116:$C$186,$D205)/J$197 -> 0 | K205: =+SUMIFS(K$116:K$186,$C$116:$C$186,$D205)/K$197 -> 0 | L205: =+SUMIFS(L$116:L$186,$C$116:$C$186,$D205)/L$197 -> 0 | M205: =+SUMIFS(M$116:M$186,$C$116:$C$186,$D205)/M$197 -> 0 | ... Q205: =+SUMIFS(Q$116:Q$186,$C$116:$C$186,$D205)/Q$197 -> 0 | R205: =+_xlfn.XLOOKUP(D205,$C$131:$C$186,$C$131:$C$186) -> Bonuses - Marketing | S205: =+SUMIFS(S$116:S$186,$C$116:$C$186,$D205)/S$197 -> 0 | T205: =+SUMIFS(T$116:T$186,$C$116:$C$186,$D205)/T$197 -> 0 | U205: =+SUMIFS(U$116:U$186,$C$116:$C$186,$D205)/U$197 -> 0
B206: Bonuses - Admin | C206: $K/Property | D206: Bonuses - Admin | F206: =+SUMIFS(F$116:F$186,$C$116:$C$186,$D206)/1000 -> 0 | G206: =+SUMIFS(G$116:G$186,$C$116:$C$186,$D206)/1000 -> 0 | H206: =+SUMIFS(H$116:H$186,$C$116:$C$186,$D206)/1000 -> 0 | I206: =+SUMIFS(I$116:I$186,$C$116:$C$186,$D206)/1000 -> 0 | J206: =+SUMIFS(J$116:J$186,$C$116:$C$186,$D206)/1000 -> 0 | K206: =+SUMIFS(K$116:K$186,$C$116:$C$186,$D206)/1000 -> 0 | L206: =+SUMIFS(L$116:L$186,$C$116:$C$186,$D206)/1000 -> 0 | M206: =+SUMIFS(M$116:M$186,$C$116:$C$186,$D206)/1000 -> 0 | ... Q206: =+SUMIFS(Q$116:Q$186,$C$116:$C$186,$D206)/1000 -> 0 | R206: =+_xlfn.XLOOKUP(D206,$C$131:$C$186,$C$131:$C$186) -> Bonuses - Admin | S206: =+SUMIFS(S$116:S$186,$C$116:$C$186,$D206)/1000 -> 0 | T206: =+SUMIFS(T$116:T$186,$C$116:$C$186,$D206)/1000 -> 0 | U206: =+SUMIFS(U$116:U$186,$C$116:$C$186,$D206)/1000 -> 0
...

Sheet Census
A1: Aster Ridge Senior Living (DEMO) -- Occupancy Report
A2: Jul 2024 - Jun 2026
A3: SYNTHETIC DEMO DATA -- NOT A REAL COMMUNITY. All figures fabricated for demonstration/testing purposes only.
A6: Month | B6: 45504 | C6: 45535 | D6: 45565 | E6: 45596 | F6: 45626 | G6: 45657 | H6: 45688 | I6: 45716 | J6: 45747 | K6: 45777 | L6: 45808 | M6: 45838 | N6: 45869 | O6: 45900 | P6: 45930 | Q6: 45961 | R6: 45991 | S6: 46022 | T6: 46053 | U6: 46081 | V6: 46112 | W6: 46142 | X6: 46173 | Y6: 46203
A7: Capacity
A8: IL | B8: 40 | C8: 40 | D8: 40 | E8: 40 | F8: 40 | G8: 40 | H8: 40 | I8: 40 | J8: 40 | K8: 40 | L8: 40 | M8: 40 | N8: 40 | O8: 40 | P8: 40 | Q8: 40 | R8: 40 | S8: 40 | T8: 40 | U8: 40 | V8: 40 | W8: 40 | X8: 40 | Y8: 40
A9: AL | B9: 30 | C9: 30 | D9: 30 | E9: 30 | F9: 30 | G9: 30 | H9: 30 | I9: 30 | J9: 30 | K9: 30 | L9: 30 | M9: 30 | N9: 30 | O9: 30 | P9: 30 | Q9: 30 | R9: 30 | S9: 30 | T9: 30 | U9: 30 | V9: 30 | W9: 30 | X9: 30 | Y9: 30
A10: MC | B10: 14 | C10: 14 | D10: 14 | E10: 14 | F10: 14 | G10: 14 | H10: 14 | I10: 14 | J10: 14 | K10: 14 | L10: 14 | M10: 14 | N10: 14 | O10: 14 | P10: 14 | Q10: 14 | R10: 14 | S10: 14 | T10: 14 | U10: 14 | V10: 14 | W10: 14 | X10: 14 | Y10: 14
A11: Total | B11: 84 | C11: 84 | D11: 84 | E11: 84 | F11: 84 | G11: 84 | H11: 84 | I11: 84 | J11: 84 | K11: 84 | L11: 84 | M11: 84 | N11: 84 | O11: 84 | P11: 84 | Q11: 84 | R11: 84 | S11: 84 | T11: 84 | U11: 84 | V11: 84 | W11: 84 | X11: 84 | Y11: 84
A13: Occupied (Month-End)
A14: IL | B14: 32 | C14: 32 | D14: 32 | E14: 33 | F14: 33 | G14: 33 | H14: 33 | I14: 33 | J14: 33 | K14: 34 | L14: 34 | M14: 34 | N14: 34 | O14: 34 | P14: 35 | Q14: 35 | R14: 36 | S14: 36 | T14: 36 | U14: 35 | V14: 36 | W14: 36 | X14: 37 | Y14: 37
A15: AL | B15: 25 | C15: 25 | D15: 25 | E15: 25 | F15: 25 | G15: 25 | H15: 26 | I15: 26 | J15: 26 | K15: 26 | L15: 26 | M15: 26 | N15: 26 | O15: 27 | P15: 27 | Q15: 26 | R15: 27 | S15: 28 | T15: 28 | U15: 27 | V15: 27 | W15: 28 | X15: 28 | Y15: 28
A16: MC | B16: 10 | C16: 10 | D16: 10 | E16: 10 | F16: 10 | G16: 10 | H16: 11 | I16: 11 | J16: 11 | K16: 11 | L16: 11 | M16: 11 | N16: 11 | O16: 12 | P16: 12 | Q16: 12 | R16: 13 | S16: 12 | T16: 12 | U16: 13 | V16: 13 | W16: 12 | X16: 13 | Y16: 13
A17: Total | B17: 67 | C17: 67 | D17: 67 | E17: 68 | F17: 68 | G17: 68 | H17: 70 | I17: 70 | J17: 70 | K17: 71 | L17: 71 | M17: 71 | N17: 71 | O17: 73 | P17: 74 | Q17: 73 | R17: 76 | S17: 76 | T17: 76 | U17: 75 | V17: 76 | W17: 76 | X17: 78 | Y17: 78
B20: Output | E20: 45869 | F20: 45900 | G20: 45930 | H20: 45961 | I20: 45991 | J20: 46022 | K20: 46053 | L20: 46081 | M20: 46112 | N20: 46142 | O20: 46173 | P20: 46203
C22: Days | E22: =DAY(E20) -> 31 | F22: =DAY(F20) -> 31 | G22: =DAY(G20) -> 30 | H22: =DAY(H20) -> 31 | I22: =DAY(I20) -> 30 | J22: =DAY(J20) -> 31 | K22: =DAY(K20) -> 31 | L22: =DAY(L20) -> 28 | ... P22: =DAY(P20) -> 30
B24: Capacity | C24: IL | E24: =N8 -> 40 | F24: =O8 -> 40 | G24: =P8 -> 40 | H24: =Q8 -> 40 | I24: =R8 -> 40 | J24: =S8 -> 40 | K24: =T8 -> 40 | L24: =U8 -> 40 | ... P24: =Y8 -> 40
B25: Capacity | C25: AL | E25: =N9 -> 30 | F25: =O9 -> 30 | G25: =P9 -> 30 | H25: =Q9 -> 30 | I25: =R9 -> 30 | J25: =S9 -> 30 | K25: =T9 -> 30 | L25: =U9 -> 30 | ... P25: =Y9 -> 30
B26: Capacity | C26: MC | E26: =N10 -> 14 | F26: =O10 -> 14 | G26: =P10 -> 14 | H26: =Q10 -> 14 | I26: =R10 -> 14 | J26: =S10 -> 14 | K26: =T10 -> 14 | L26: =U10 -> 14 | ... P26: =Y10 -> 14
B27: Capacity | C27: Total | E27: =SUM(E24:E26) -> 84 | F27: =SUM(F24:F26) -> 84 | G27: =SUM(G24:G26) -> 84 | H27: =SUM(H24:H26) -> 84 | I27: =SUM(I24:I26) -> 84 | J27: =SUM(J24:J26) -> 84 | K27: =SUM(K24:K26) -> 84 | L27: =SUM(L24:L26) -> 84 | ... P27: =SUM(P24:P26) -> 84
B29: Occupied | C29: IL | E29: =N14 -> 34 | F29: =O14 -> 34 | G29: =P14 -> 35 | H29: =Q14 -> 35 | I29: =R14 -> 36 | J29: =S14 -> 36 | K29: =T14 -> 36 | L29: =U14 -> 35 | ... P29: =Y14 -> 37
B30: Occupied | C30: AL | E30: =N15 -> 26 | F30: =O15 -> 27 | G30: =P15 -> 27 | H30: =Q15 -> 26 | I30: =R15 -> 27 | J30: =S15 -> 28 | K30: =T15 -> 28 | L30: =U15 -> 27 | ... P30: =Y15 -> 28
B31: Occupied | C31: MC | E31: =N16 -> 11 | F31: =O16 -> 12 | G31: =P16 -> 12 | H31: =Q16 -> 12 | I31: =R16 -> 13 | J31: =S16 -> 12 | K31: =T16 -> 12 | L31: =U16 -> 13 | ... P31: =Y16 -> 13
B32: Occupied | C32: Total | E32: =SUM(E29:E31) -> 71 | F32: =SUM(F29:F31) -> 73 | G32: =SUM(G29:G31) -> 74 | H32: =SUM(H29:H31) -> 73 | I32: =SUM(I29:I31) -> 76 | J32: =SUM(J29:J31) -> 76 | K32: =SUM(K29:K31) -> 76 | L32: =SUM(L29:L31) -> 75 | ... P32: =SUM(P29:P31) -> 78
B34: Avg Occ % | C34: IL | E34: =E29/E24 -> 0.85 | F34: =F29/F24 -> 0.85 | G34: =G29/G24 -> 0.875 | H34: =H29/H24 -> 0.875 | I34: =I29/I24 -> 0.9 | J34: =J29/J24 -> 0.9 | K34: =K29/K24 -> 0.9 | L34: =L29/L24 -> 0.875 | ... P34: =P29/P24 -> 0.925
B35: Avg Occ % | C35: AL | E35: =E30/E25 -> 0.86666667 | F35: =F30/F25 -> 0.9 | G35: =G30/G25 -> 0.9 | H35: =H30/H25 -> 0.86666667 | I35: =I30/I25 -> 0.9 | J35: =J30/J25 -> 0.93333333 | K35: =K30/K25 -> 0.93333333 | L35: =L30/L25 -> 0.9 | ... P35: =P30/P25 -> 0.93333333
B36: Avg Occ % | C36: MC | E36: =E31/E26 -> 0.78571429 | F36: =F31/F26 -> 0.85714286 | G36: =G31/G26 -> 0.85714286 | H36: =H31/H26 -> 0.85714286 | I36: =I31/I26 -> 0.92857143 | J36: =J31/J26 -> 0.85714286 | K36: =K31/K26 -> 0.85714286 | L36: =L31/L26 -> 0.92857143 | ... P36: =P31/P26 -> 0.92857143

Sheet AR PnL Mapping
A2: Check | C2: Tag | D2: Questions & Comments | E2: List of Tags
C3: REVENUE | E3: Rent Revenue - AL
A4: =IF(COUNTIF($E:$E,B4),"Yes","No") -> Yes | B4: Rent Revenue - IL | C4: 4010 - Rent Income - IL | E4: Rent Revenue - IL
A5: =IF(COUNTIF($E:$E,B5),"Yes","No") -> Yes | B5: Rent Revenue - AL | C5: 4020 - Rent Income - AL | E5: Rent Revenue - TC
A6: =IF(COUNTIF($E:$E,B6),"Yes","No") -> Yes | B6: Rent Revenue - MC | C6: 4030 - Rent Income - MC | E6: Rent Revenue - MC
C7: TOTAL RENT REVENUE | E7: Rent Concessions
A8: =IF(COUNTIF($E:$E,B8),"Yes","No") -> Yes | B8: Care Revenue - AL | C8: 4110 - Care Level Income - AL | E8: Other Revenue
A9: =IF(COUNTIF($E:$E,B9),"Yes","No") -> Yes | B9: Care Revenue - MC | C9: 4120 - Care Level Income - MC | E9: Commercial Lease Revenue
C10: TOTAL CARE REVENUE | E10: Rent - Second Person
A11: =IF(COUNTIF($E:$E,B11),"Yes","No") -> Yes | B11: Rent - Second Person | C11: 4210 - Second Person Fees | E11: Care Revenue - AL
A12: =IF(COUNTIF($E:$E,B12),"Yes","No") -> Yes | B12: Community Fees | C12: 4310 - Community Fees | E12: Care Revenue - MC
A13: =IF(COUNTIF($E:$E,B13),"Yes","No") -> Yes | B13: Other Revenue | C13: 4410 - Other Resident Income | E13: Community Fees
A14: =IF(COUNTIF($E:$E,B14),"Yes","No") -> Yes | B14: Other Revenue | C14: 4510 - Guest Meals & Ancillary | E14: Wages - Admin
C15: TOTAL OTHER REVENUE | E15: Wages - Culinary
C16: TOTAL REVENUE | E16: Wages - Direct Care
C17: EXPENSES | E17: Wages - Activities
A18: =IF(COUNTIF($E:$E,B18),"Yes","No") -> Yes | B18: Wages - Culinary | C18: 6110 - Dining Wages | E18: Wages - Housekeeping
A19: =IF(COUNTIF($E:$E,B19),"Yes","No") -> Yes | B19: Wages - Culinary | C19: 6120 - Dining Director | E19: Wages - Maintenance
A20: =IF(COUNTIF($E:$E,B20),"Yes","No") -> Yes | B20: Raw Food | C20: 7010 - Raw Food | E20: Wages - Marketing
A21: =IF(COUNTIF($E:$E,B21),"Yes","No") -> Yes | B21: Culinary | C21: 7020 - Dining Supplies | E21: Bonuses - Marketing
C22: TOTAL CULINARY EXPENSES | E22: Bonuses - Admin
A23: =IF(COUNTIF($E:$E,B23),"Yes","No") -> Yes | B23: Wages - Activities | C23: 6410 - Activities Wages | E23: Contract Labor - Maintenance
C24: TOTAL ACTIVITIES EXPENSES | E24: Contract Labor - Marketing
A25: =IF(COUNTIF($E:$E,B25),"Yes","No") -> Yes | B25: Wages - Direct Care | C25: 6010 - Caregiver Wages | E25: Contract Labor - Culinary
A26: =IF(COUNTIF($E:$E,B26),"Yes","No") -> Yes | B26: Wages - Direct Care | C26: 6020 - Med Tech Wages | E26: Contract Labor - Activities
A27: =IF(COUNTIF($E:$E,B27),"Yes","No") -> Yes | B27: Wages - Direct Care | C27: 6030 - Wellness Director | E27: Contract Labor - Admin
A28: =IF(COUNTIF($E:$E,B28),"Yes","No") -> Yes | B28: Direct Care | C28: 7210 - Care Supplies | E28: Contract Labor - Direct Care
C29: TOTAL WELLNESS - NURSING EXPENSES | E29: Contract Labor - Housekeeping
A30: =IF(COUNTIF($E:$E,B30),"Yes","No") -> Yes | B30: Wages - Maintenance | C30: 6310 - Maintenance Wages | E30: Benefits - Activities
A31: =IF(COUNTIF($E:$E,B31),"Yes","No") -> Yes | B31: Maintenance | C31: 7610 - Repairs & Maintenance | E31: Benefits - Culinary
C32: TOTAL MAINTENANCE EXPENSES | E32: Benefits - Direct Care
A33: =IF(COUNTIF($E:$E,B33),"Yes","No") -> Yes | B33: Utilities | C33: 7510 - Electricity | E33: Benefits - Marketing
A34: =IF(COUNTIF($E:$E,B34),"Yes","No") -> Yes | B34: Utilities | C34: 7520 - Gas | E34: Benefits - Housekeeping
A35: =IF(COUNTIF($E:$E,B35),"Yes","No") -> Yes | B35: Utilities | C35: 7530 - Water/Sewer | E35: Benefits - Maintenance
A36: =IF(COUNTIF($E:$E,B36),"Yes","No") -> Yes | B36: Utilities | C36: 7540 - Trash | E36: Benefits - Admin
C37: TOTAL UTILITIES EXPENSES | E37: Raw Food
A38: =IF(COUNTIF($E:$E,B38),"Yes","No") -> Yes | B38: Wages - Housekeeping | C38: 6210 - Housekeeping Wages | E38: Culinary
A39: =IF(COUNTIF($E:$E,B39),"Yes","No") -> Yes | B39: Housekeeping | C39: 7110 - Housekeeping Supplies | E39: Activities
C40: TOTAL HOUSEKEEPING EXPENSE | E40: Direct Care
A41: =IF(COUNTIF($E:$E,B41),"Yes","No") -> Yes | B41: Wages - Marketing | C41: 6630 - Sales & Marketing Wages | E41: COGS
A42: =IF(COUNTIF($E:$E,B42),"Yes","No") -> Yes | B42: Marketing | C42: 7410 - Marketing & Advertising | E42: Maintenance
C43: TOTAL MARKETING EXPENSES | E43: Utilities
A44: =IF(COUNTIF($E:$E,B44),"Yes","No") -> Yes | B44: Wages - Admin | C44: 6510 - Concierge Wages | E44: Housekeeping
A45: =IF(COUNTIF($E:$E,B45),"Yes","No") -> Yes | B45: Wages - Admin | C45: 6610 - Business Office Manager | E45: Marketing
A46: =IF(COUNTIF($E:$E,B46),"Yes","No") -> Yes | B46: Wages - Admin | C46: 6620 - Executive Director | E46: Marketing - Contract Services
A47: =IF(COUNTIF($E:$E,B47),"Yes","No") -> Yes | B47: Admin - IT | C47: 7710 - IT & Telephone | D47: Lumped IT & Telephone, no split on this HF -- best guess Admin - IT; may include telephone spend (Admin - Telephone) | E47: Marketing - Referral Fees
A48: =IF(COUNTIF($E:$E,B48),"Yes","No") -> Yes | B48: Admin | C48: 7990 - Other G&A | E48: Admin
C49: TOTAL ADMINISTRATION EXPENSES | E49: Admin - Health & Dental
A50: =IF(COUNTIF($E:$E,B50),"Yes","No") -> Yes | B50: Benefits - Admin | C50: 6710 - Payroll Taxes | D50: Payroll Taxes pooled co-wide (HF: no dept split) -- no company-wide Benefits tag; best guess Benefits - Admin | E50: Admin - Vehicle Lease
A51: =IF(COUNTIF($E:$E,B51),"Yes","No") -> Yes | B51: Benefits - Admin | C51: 6720 - Employee Benefits | D51: Employee Benefits pooled co-wide (HF: no dept split) -- no company-wide Benefits tag; best guess Benefits - Admin | E51: Admin - Travel
A52: =IF(COUNTIF($E:$E,B52),"Yes","No") -> Yes | B52: Insurance - Workers Comp | C52: 6730 - Workers Comp | E52: Admin - Telephone
C53: TOTAL PAYROLL TAXES and BENEFITS EXPENSES | E53: Admin - Legal
A54: =IF(COUNTIF($E:$E,B54),"Yes","No") -> Yes | B54: Business Insurance | C54: 7810 - Insurance | E54: Admin - Bad Debt
A55: =IF(COUNTIF($E:$E,B55),"Yes","No") -> Yes | B55: Real Estate Taxes | C55: 7820 - Real Estate Taxes | E55: Admin - IT
A56: =IF(COUNTIF($E:$E,B56),"Yes","No") -> Yes | B56: Management Fee | C56: 7910 - Management Fee | E56: Admin - Bank & Payroll Fees
C57: TOTAL NON-DEPARTMENTAL EXPENSES | E57: Admin - Other Expense
C58: TOTAL OPERATING EXPENSES | E58: Insurance - Workers Comp
C59: NET OPERATING INCOME | E59: Real Estate Taxes
C60: Margin | E60: Business Insurance
E61: Insurance - Other
E62: Other Taxes
E63: Non-Departmental
E64: Management Fee
E65: Ignore

Sheet AR Historical Financials
C2: Aster Ridge Senior Living (DEMO)
C3: Statement (12 months)
C4: Period = Jul 2025 - Jun 2026
C5: Book = Accrual ; Tree = wlf_cf
A6: x | C6: REVENUE | E6: 45869 | F6: 45900 | G6: 45930 | H6: 45961 | I6: 45991 | J6: 46022 | K6: 46053 | L6: 46081 | M6: 46112 | N6: 46142 | O6: 46173 | P6: 46203 | Q6: Total
C8: =IF(S8="",T8,S8&" - "&T8) -> 4010 - Rent Income - IL | E8: 130152 | F8: 130398 | G8: 133507 | H8: 132350 | I8: 135400 | J8: 135680 | K8: 136760 | L8: 133994 | M8: 138063 | N8: 137300 | O8: 139892 | P8: 140535 | Q8: =SUM(E8:P8) -> 1624031 | S8: 4010 | T8: Rent Income - IL
C9: =IF(S9="",T9,S9&" - "&T9) -> 4020 - Rent Income - AL | E9: 120910 | F9: 125160 | G9: 124124 | H9: 118673 | I9: 123170 | J9: 128565 | K9: 129671 | L9: 125562 | M9: 125145 | N9: 128700 | O9: 127791 | P9: 128925 | Q9: =SUM(E9:P9) -> 1506396 | S9: 4020 | T9: Rent Income - AL
C10: =IF(S10="",T10,S10&" - "&T10) -> 4030 - Rent Income - MC | E10: 86707 | F10: 93912 | G10: 93135 | H10: 92846 | I10: 101036 | J10: 94072 | K10: 94660 | L10: 102463 | M10: 101721 | N10: 93124 | O10: 100585 | P10: 101595 | Q10: =SUM(E10:P10) -> 1155856 | S10: 4030 | T10: Rent Income - MC
A12: x | C12: TOTAL RENT REVENUE | E12: =E8+E9+E10 -> 337769 | F12: =F8+F9+F10 -> 349470 | G12: =G8+G9+G10 -> 350766 | H12: =H8+H9+H10 -> 343869 | I12: =I8+I9+I10 -> 359606 | J12: =J8+J9+J10 -> 358317 | K12: =K8+K9+K10 -> 361091 | L12: =L8+L9+L10 -> 362019 | ... Q12: =Q8+Q9+Q10 -> 4286283
C14: =IF(S14="",T14,S14&" - "&T14) -> 4110 - Care Level Income - AL | E14: 25794 | F14: 26554 | G14: 26411 | H14: 25486 | I14: 26677 | J14: 27880 | K14: 27928 | L14: 26782 | M14: 26550 | N14: 27389 | O14: 27449 | P14: 27660 | Q14: =SUM(E14:P14) -> 322560 | S14: 4110 | T14: Care Level Income - AL
C15: =IF(S15="",T15,S15&" - "&T15) -> 4120 - Care Level Income - MC | E15: 15207 | F15: 16471 | G15: 16462 | H15: 16569 | I15: 18104 | J15: 16781 | K15: 16726 | L15: 17969 | M15: 17842 | N15: 16463 | O15: 17953 | P15: 18000 | Q15: =SUM(E15:P15) -> 204547 | S15: 4120 | T15: Care Level Income - MC
A17: x | C17: TOTAL CARE REVENUE | E17: =E14+E15 -> 41001 | F17: =F14+F15 -> 43025 | G17: =G14+G15 -> 42873 | H17: =H14+H15 -> 42055 | I17: =I14+I15 -> 44781 | J17: =J14+J15 -> 44661 | K17: =K14+K15 -> 44654 | L17: =L14+L15 -> 44751 | ... Q17: =Q14+Q15 -> 527107
C19: =IF(S19="",T19,S19&" - "&T19) -> 4210 - Second Person Fees | E19: 7297 | F19: 7396 | G19: 7551 | H19: 7493 | I19: 7787 | J19: 7905 | K19: 7847 | L19: 7539 | M19: 7638 | N19: 7795 | O19: 7986 | P19: 7960 | Q19: =SUM(E19:P19) -> 92194 | S19: 4210 | T19: Second Person Fees
C20: =IF(S20="",T20,S20&" - "&T20) -> 4310 - Community Fees | E20: 4087 | F20: 9901 | G20: 5616 | H20: 3000 | I20: 13391 | J20: 3969 | K20: 3000 | L20: 3000 | M20: 6430 | N20: 4092 | O20: 9873 | P20: 3000 | Q20: =SUM(E20:P20) -> 69359 | S20: 4310 | T20: Community Fees
C21: =IF(S21="",T21,S21&" - "&T21) -> 4410 - Other Resident Income | E21: 3577 | F21: 3254 | G21: 2852 | H21: 2960 | I21: 3420 | J21: 3557 | K21: 3171 | L21: 2827 | M21: 3029 | N21: 3481 | O21: 3521 | P21: 3091 | Q21: =SUM(E21:P21) -> 38740 | S21: 4410 | T21: Other Resident Income
C22: =IF(S22="",T22,S22&" - "&T22) -> 4510 - Guest Meals & Ancillary | E22: 2517 | F22: 1915 | G22: 2183 | H22: 2715 | I22: 2310 | J22: 1882 | K22: 2397 | L22: 2693 | M22: 2102 | N22: 1958 | O22: 2586 | P22: 2568 | Q22: =SUM(E22:P22) -> 27826 | S22: 4510 | T22: Guest Meals & Ancillary
A24: x | C24: TOTAL OTHER REVENUE | E24: =E19+E20+E21+E22 -> 17478 | F24: =F19+F20+F21+F22 -> 22466 | G24: =G19+G20+G21+G22 -> 18202 | H24: =H19+H20+H21+H22 -> 16168 | I24: =I19+I20+I21+I22 -> 26908 | J24: =J19+J20+J21+J22 -> 17313 | K24: =K19+K20+K21+K22 -> 16415 | L24: =L19+L20+L21+L22 -> 16059 | ... Q24: =Q19+Q20+Q21+Q22 -> 228119
A26: x | C26: TOTAL REVENUE | E26: =E12+E17+E24 -> 396248 | F26: =F12+F17+F24 -> 414961 | G26: =G12+G17+G24 -> 411841 | H26: =H12+H17+H24 -> 402092 | I26: =I12+I17+I24 -> 431295 | J26: =J12+J17+J24 -> 420291 | K26: =K12+K17+K24 -> 422160 | L26: =L12+L17+L24 -> 422829 | ... Q26: =Q12+Q17+Q24 -> 5041509
A28: x | C28: EXPENSES
C30: =IF(S30="",T30,S30&" - "&T30) -> 6110 - Dining Wages | E30: 24823 | F30: 24567 | G30: 24610 | H30: 24904 | I30: 25129 | J30: 25038 | K30: 24731 | L30: 24543 | M30: 24680 | N30: 24992 | O30: 25137 | P30: 24958 | Q30: =SUM(E30:P30) -> 298112 | S30: 6110 | T30: Dining Wages
C31: =IF(S31="",T31,S31&" - "&T31) -> 6120 - Dining Director | E31: 4749 | F31: 4728 | G31: 4768 | H31: 4826 | I31: 4838 | J31: 4791 | K31: 4736 | L31: 4734 | M31: 4786 | N31: 4836 | O31: 4829 | P31: 4773 | Q31: =SUM(E31:P31) -> 57394 | S31: 6120 | T31: Dining Director
C32: =IF(S32="",T32,S32&" - "&T32) -> 7010 - Raw Food | E32: 14219 | F32: 14256 | G32: 14128 | H32: 13913 | I32: 13740 | J32: 13716 | K32: 13854 | L32: 14071 | M32: 14235 | N32: 14247 | O32: 14099 | P32: 13882 | Q32: =SUM(E32:P32) -> 168360 | S32: 7010 | T32: Raw Food
C33: =IF(S33="",T33,S33&" - "&T33) -> 7020 - Dining Supplies | E33: 2252 | F33: 2234 | G33: 2193 | H33: 2165 | I33: 2177 | J33: 2217 | K33: 2249 | L33: 2243 | M33: 2205 | N33: 2169 | O33: 2169 | P33: 2205 | Q33: =SUM(E33:P33) -> 26478 | S33: 7020 | T33: Dining Supplies
A35: x | C35: TOTAL CULINARY EXPENSES | E35: =E30+E31+E32+E33 -> 46043 | F35: =F30+F31+F32+F33 -> 45785 | G35: =G30+G31+G32+G33 -> 45699 | H35: =H30+H31+H32+H33 -> 45808 | I35: =I30+I31+I32+I33 -> 45884 | J35: =J30+J31+J32+J33 -> 45762 | K35: =K30+K31+K32+K33 -> 45570 | L35: =L30+L31+L32+L33 -> 45591 | ... Q35: =Q30+Q31+Q32+Q33 -> 550344
C37: =IF(S37="",T37,S37&" - "&T37) -> 6410 - Activities Wages | E37: 6209 | F37: 6286 | G37: 6331 | H37: 6294 | I37: 6215 | J37: 6181 | K37: 6229 | L37: 6306 | M37: 6328 | N37: 6271 | O37: 6198 | P37: 6187 | Q37: =SUM(E37:P37) -> 75035 | S37: 6410 | T37: Activities Wages
A39: x | C39: TOTAL ACTIVITIES EXPENSES | E39: =E37 -> 6209 | F39: =F37 -> 6286 | G39: =G37 -> 6331 | H39: =H37 -> 6294 | I39: =I37 -> 6215 | J39: =J37 -> 6181 | K39: =K37 -> 6229 | L39: =L37 -> 6306 | ... Q39: =Q37 -> 75035
C41: =IF(S41="",T41,S41&" - "&T41) -> 6010 - Caregiver Wages | E41: 45613 | F41: 45404 | G41: 44841 | H41: 44539 | I41: 44829 | J41: 45393 | K41: 45615 | L41: 45253 | M41: 44701 | N41: 44564 | O41: 44990 | P41: 45515 | Q41: =SUM(E41:P41) -> 541257 | S41: 6010 | T41: Caregiver Wages
C42: =IF(S42="",T42,S42&" - "&T42) -> 6020 - Med Tech Wages | E42: 17206 | F42: 17028 | G42: 16842 | H42: 16850 | I42: 17044 | J42: 17212 | K42: 17170 | L42: 16964 | M42: 16820 | N42: 16894 | O42: 17106 | P42: 17224 | Q42: =SUM(E42:P42) -> 204360 | S42: 6020 | T42: Med Tech Wages
C43: =IF(S43="",T43,S43&" - "&T43) -> 6030 - Wellness Director | E43: 5554 | F43: 5485 | G43: 5454 | H43: 5495 | I43: 5564 | J43: 5584 | K43: 5535 | L43: 5469 | M43: 5459 | N43: 5516 | O43: 5577 | P43: 5576 | Q43: =SUM(E43:P43) -> 66268 | S43: 6030 | T43: Wellness Director
C44: =IF(S44="",T44,S44&" - "&T44) -> 7210 - Care Supplies | E44: 3340 | F44: 3258 | G44: 3265 | H44: 3350 | I44: 3372 | J44: 3294 | K44: 3246 | L44: 3308 | M44: 3376 | N44: 3338 | O44: 3257 | P44: 3267 | Q44: =SUM(E44:P44) -> 39671 | S44: 7210 | T44: Care Supplies
A46: x | C46: TOTAL WELLNESS - NURSING EXPENSES | E46: =E41+E42+E43+E44 -> 71713 | F46: =F41+F42+F43+F44 -> 71175 | G46: =G41+G42+G43+G44 -> 70402 | H46: =H41+H42+H43+H44 -> 70234 | I46: =I41+I42+I43+I44 -> 70809 | J46: =J41+J42+J43+J44 -> 71483 | K46: =K41+K42+K43+K44 -> 71566 | L46: =L41+L42+L43+L44 -> 70994 | ... Q46: =Q41+Q42+Q43+Q44 -> 851556
C48: =IF(S48="",T48,S48&" - "&T48) -> 6310 - Maintenance Wages | E48: 8912 | F48: 8996 | G48: 9102 | H48: 9114 | I48: 9019 | J48: 8921 | K48: 8927 | L48: 9030 | M48: 9118 | N48: 9094 | O48: 8985 | P48: 8910 | Q48: =SUM(E48:P48) -> 108128 | S48: 6310 | T48: Maintenance Wages
C49: =IF(S49="",T49,S49&" - "&T49) -> 7610 - Repairs & Maintenance | E49: 6661 | F49: 6442 | G49: 6360 | H49: 6478 | I49: 6707 | J49: 6873 | K49: 6850 | L49: 6657 | M49: 6439 | N49: 6360 | O49: 6482 | P49: 6711 | Q49: =SUM(E49:P49) -> 79020 | S49: 7610 | T49: Repairs & Maintenance
A51: x | C51: TOTAL MAINTENANCE EXPENSES | E51: =E48+E49 -> 15573 | F51: =F48+F49 -> 15438 | G51: =G48+G49 -> 15462 | H51: =H48+H49 -> 15592 | I51: =I48+I49 -> 15726 | J51: =J48+J49 -> 15794 | K51: =K48+K49 -> 15777 | L51: =L48+L49 -> 15687 | ... Q51: =Q48+Q49 -> 187148
C53: =IF(S53="",T53,S53&" - "&T53) -> 7510 - Electricity | E53: 11592 | F53: 12075 | G53: 10143 | H53: 8694 | I53: 8694 | J53: 10143 | K53: 11109 | L53: 10626 | M53: 9177 | N53: 8211 | O53: 8694 | P53: 10626 | Q53: =SUM(E53:P53) -> 119784 | S53: 7510 | T53: Electricity
C54: =IF(S54="",T54,S54&" - "&T54) -> 7520 - Gas | E54: 1573 | F54: 1573 | G54: 1923 | H54: 2972 | I54: 4370 | J54: 5419 | K54: 5594 | L54: 5244 | M54: 4195 | N54: 2972 | O54: 2098 | P54: 1748 | Q54: =SUM(E54:P54) -> 39681 | S54: 7520 | T54: Gas
C55: =IF(S55="",T55,S55&" - "&T55) -> 7530 - Water/Sewer | E55: 4126 | F55: 4126 | G55: 3767 | H55: 3588 | I55: 3409 | J55: 3409 | K55: 3409 | L55: 3409 | M55: 3588 | N55: 3588 | O55: 3767 | P55: 4126 | Q55: =SUM(E55:P55) -> 44312 | S55: 7530 | T55: Water/Sewer
C56: =IF(S56="",T56,S56&" - "&T56) -> 7540 - Trash | E56: 1564 | F56: 1564 | G56: 1564 | H56: 1564 | I56: 1564 | J56: 1564 | K56: 1564 | L56: 1564 | M56: 1564 | N56: 1564 | O56: 1564 | P56: 1564 | Q56: =SUM(E56:P56) -> 18768 | S56: 7540 | T56: Trash
A58: x | C58: TOTAL UTILITIES EXPENSES | E58: =E53+E54+E55+E56 -> 18855 | F58: =F53+F54+F55+F56 -> 19338 | G58: =G53+G54+G55+G56 -> 17397 | H58: =H53+H54+H55+H56 -> 16818 | I58: =I53+I54+I55+I56 -> 18037 | J58: =J53+J54+J55+J56 -> 20535 | K58: =K53+K54+K55+K56 -> 21676 | L58: =L53+L54+L55+L56 -> 20843 | ... Q58: =Q53+Q54+Q55+Q56 -> 222545
C60: =IF(S60="",T60,S60&" - "&T60) -> 6210 - Housekeeping Wages | E60: 12278 | F60: 12315 | G60: 12466 | H60: 12567 | I60: 12507 | J60: 12352 | K60: 12271 | L60: 12353 | M60: 12508 | N60: 12567 | O60: 12465 | P60: 12314 | Q60: =SUM(E60:P60) -> 148963 | S60: 6210 | T60: Housekeeping Wages
C61: =IF(S61="",T61,S61&" - "&T61) -> 7110 - Housekeeping Supplies | E61: 2620 | F61: 2568 | G61: 2526 | H61: 2548 | I61: 2606 | J61: 2626 | K61: 2582 | L61: 2531 | M61: 2537 | N61: 2593 | O61: 2627 | P61: 2596 | Q61: =SUM(E61:P61) -> 30960 | S61: 7110 | T61: Housekeeping Supplies
A63: x | C63: TOTAL HOUSEKEEPING EXPENSE | E63: =E60+E61 -> 14898 | F63: =F60+F61 -> 14883 | G63: =G60+G61 -> 14992 | H63: =H60+H61 -> 15115 | I63: =I60+I61 -> 15113 | J63: =J60+J61 -> 14978 | K63: =K60+K61 -> 14853 | L63: =L60+L61 -> 14884 | ... Q63: =Q60+Q61 -> 179923
C65: =IF(S65="",T65,S65&" - "&T65) -> 6630 - Sales & Marketing Wages | E65: 7075 | F65: 7019 | G65: 6933 | H65: 6912 | I65: 6978 | J65: 7059 | K65: 7067 | L65: 6993 | M65: 6918 | N65: 6924 | O65: 7005 | P65: 7072 | Q65: =SUM(E65:P65) -> 83955 | S65: 6630 | T65: Sales & Marketing Wages
C66: =IF(S66="",T66,S66&" - "&T66) -> 7410 - Marketing & Advertising | E66: 5535 | F66: 5400 | G66: 5242 | H66: 5118 | I66: 5069 | J66: 5114 | K66: 5236 | L66: 5393 | M66: 5530 | N66: 5600 | O66: 5577 | P66: 5470 | Q66: =SUM(E66:P66) -> 64284 | S66: 7410 | T66: Marketing & Advertising
A68: x | C68: TOTAL MARKETING EXPENSES | E68: =E65+E66 -> 12610 | F68: =F65+F66 -> 12419 | G68: =G65+G66 -> 12175 | H68: =H65+H66 -> 12030 | I68: =I65+I66 -> 12047 | J68: =J65+J66 -> 12173 | K68: =K65+K66 -> 12303 | L68: =L65+L66 -> 12386 | ... Q68: =Q65+Q66 -> 148239
C70: =IF(S70="",T70,S70&" - "&T70) -> 6510 - Concierge Wages | E70: 7536 | F70: 7621 | G70: 7621 | H70: 7537 | I70: 7460 | J70: 7475 | K70: 7565 | L70: 7632 | M70: 7603 | N70: 7509 | O70: 7454 | P70: 7497 | Q70: =SUM(E70:P70) -> 90510 | S70: 6510 | T70: Concierge Wages
C71: =IF(S71="",T71,S71&" - "&T71) -> 6610 - Business Office Manager | E71: 5183 | F71: 5214 | G71: 5177 | H71: 5113 | I71: 5091 | J71: 5136 | K71: 5198 | L71: 5210 | M71: 5159 | N71: 5100 | O71: 5098 | P71: 5155 | Q71: =SUM(E71:P71) -> 61834 | S71: 6610 | T71: Business Office Manager
C72: =IF(S72="",T72,S72&" - "&T72) -> 6620 - Executive Director | E72: 8555 | F72: 8545 | G72: 8446 | H72: 8367 | I72: 8394 | J72: 8497 | K72: 8565 | L72: 8522 | M72: 8416 | N72: 8362 | O72: 8420 | P72: 8526 | Q72: =SUM(E72:P72) -> 101615 | S72: 6620 | T72: Executive Director
C73: =IF(S73="",T73,S73&" - "&T73) -> 7710 - IT & Telephone | E73: 2760 | F73: 2760 | G73: 2760 | H73: 2760 | I73: 2760 | J73: 2760 | K73: 2760 | L73: 2760 | M73: 2760 | N73: 2760 | O73: 2760 | P73: 2760 | Q73: =SUM(E73:P73) -> 33120 | S73: 7710 | T73: IT & Telephone
C74: =IF(S74="",T74,S74&" - "&T74) -> 7990 - Other G&A | E74: 4128 | F74: 4162 | G74: 4340 | H74: 4296 | I74: 4120 | J74: 4175 | K74: 4347 | L74: 4282 | M74: 4114 | N74: 4189 | O74: 4353 | P74: 4268 | Q74: =SUM(E74:P74) -> 50774 | S74: 7990 | T74: Other G&A
A76: x | C76: TOTAL ADMINISTRATION EXPENSES | E76: =E70+E71+E72+E73+E74 -> 28162 | F76: =F70+F71+F72+F73+F74 -> 28302 | G76: =G70+G71+G72+G73+G74 -> 28344 | H76: =H70+H71+H72+H73+H74 -> 28073 | I76: =I70+I71+I72+I73+I74 -> 27825 | J76: =J70+J71+J72+J73+J74 -> 28043 | K76: =K70+K71+K72+K73+K74 -> 28435 | L76: =L70+L71+L72+L73+L74 -> 28406 | ... Q76: =Q70+Q71+Q72+Q73+Q74 -> 337853
C78: =IF(S78="",T78,S78&" - "&T78) -> 6710 - Payroll Taxes | E78: 14601 | F78: 14555 | G78: 14496 | H78: 14489 | I78: 14541 | J78: 14596 | K78: 14593 | L78: 14536 | M78: 14487 | N78: 14500 | O78: 14560 | P78: 14602 | Q78: =SUM(E78:P78) -> 174556 | S78: 6710 | T78: Payroll Taxes
C79: =IF(S79="",T79,S79&" - "&T79) -> 6720 - Employee Benefits | E79: 11296 | F79: 11335 | G79: 11321 | H79: 11262 | I79: 11185 | J79: 11126 | K79: 11114 | L79: 11153 | M79: 11226 | N79: 11298 | O79: 11335 | P79: 11320 | Q79: =SUM(E79:P79) -> 134971 | S79: 6720 | T79: Employee Benefits
C80: =IF(S80="",T80,S80&" - "&T80) -> 6730 - Workers Comp | E80: 3051 | F80: 3062 | G80: 3066 | H80: 3064 | I80: 3054 | J80: 3040 | K80: 3025 | L80: 3013 | M80: 3006 | N80: 3007 | O80: 3015 | P80: 3028 | Q80: =SUM(E80:P80) -> 36431 | S80: 6730 | T80: Workers Comp
A82: x | C82: TOTAL PAYROLL TAXES and BENEFITS EXPENSES | E82: =E78+E79+E80 -> 28948 | F82: =F78+F79+F80 -> 28952 | G82: =G78+G79+G80 -> 28883 | H82: =H78+H79+H80 -> 28815 | I82: =I78+I79+I80 -> 28780 | J82: =J78+J79+J80 -> 28762 | K82: =K78+K79+K80 -> 28732 | L82: =L78+L79+L80 -> 28702 | ... Q82: =Q78+Q79+Q80 -> 345958
C84: =IF(S84="",T84,S84&" - "&T84) -> 7810 - Insurance | E84: 10120 | F84: 10120 | G84: 10120 | H84: 10120 | I84: 10120 | J84: 10120 | K84: 10120 | L84: 10120 | M84: 10120 | N84: 10120 | O84: 10120 | P84: 10120 | Q84: =SUM(E84:P84) -> 121440 | S84: 7810 | T84: Insurance
C85: =IF(S85="",T85,S85&" - "&T85) -> 7820 - Real Estate Taxes | E85: 12880 | F85: 12880 | G85: 12880 | H85: 12880 | I85: 12880 | J85: 12880 | K85: 12880 | L85: 12880 | M85: 12880 | N85: 12880 | O85: 12880 | P85: 12880 | Q85: =SUM(E85:P85) -> 154560 | S85: 7820 | T85: Real Estate Taxes
C86: =IF(S86="",T86,S86&" - "&T86) -> 7910 - Management Fee | E86: 19812 | F86: 20748 | G86: 20592 | H86: 20105 | I86: 21565 | J86: 21015 | K86: 21108 | L86: 21141 | M86: 21426 | N86: 21015 | O86: 21882 | P86: 21667 | Q86: =SUM(E86:P86) -> 252076 | S86: 7910 | T86: Management Fee
A88: x | C88: TOTAL NON-DEPARTMENTAL EXPENSES | E88: =E84+E85+E86 -> 42812 | F88: =F84+F85+F86 -> 43748 | G88: =G84+G85+G86 -> 43592 | H88: =H84+H85+H86 -> 43105 | I88: =I84+I85+I86 -> 44565 | J88: =J84+J85+J86 -> 44015 | K88: =K84+K85+K86 -> 44108 | L88: =L84+L85+L86 -> 44141 | ... Q88: =Q84+Q85+Q86 -> 528076
A90: x | C90: TOTAL OPERATING EXPENSES | E90: =E35+E39+E46+E51+E58+E63+E68+E76+E82+E88 -> 285823 | F90: =F35+F39+F46+F51+F58+F63+F68+F76+F82+F88 -> 286326 | G90: =G35+G39+G46+G51+G58+G63+G68+G76+G82+G88 -> 283277 | H90: =H35+H39+H46+H51+H58+H63+H68+H76+H82+H88 -> 281884 | I90: =I35+I39+I46+I51+I58+I63+I68+I76+I82+I88 -> 285001 | J90: =J35+J39+J46+J51+J58+J63+J68+J76+J82+J88 -> 287726 | K90: =K35+K39+K46+K51+K58+K63+K68+K76+K82+K88 -> 289249 | L90: =L35+L39+L46+L51+L58+L63+L68+L76+L82+L88 -> 287940 | ... Q90: =Q35+Q39+Q46+Q51+Q58+Q63+Q68+Q76+Q82+Q88 -> 3426677
A92: x | C92: NET OPERATING INCOME | E92: =E26-E90 -> 110425 | F92: =F26-F90 -> 128635 | G92: =G26-G90 -> 128564 | H92: =H26-H90 -> 120208 | I92: =I26-I90 -> 146294 | J92: =J26-J90 -> 132565 | K92: =K26-K90 -> 132911 | L92: =L26-L90 -> 134889 | ... Q92: =Q26-Q90 -> 1614832
C93: Margin | E93: =IFERROR(E92/E26,0) -> 0.27867649 | F93: =IFERROR(F92/F26,0) -> 0.30999299 | G93: =IFERROR(G92/G26,0) -> 0.31216902 | H93: =IFERROR(H92/H26,0) -> 0.29895646 | I93: =IFERROR(I92/I26,0) -> 0.33919707 | J93: =IFERROR(J92/J26,0) -> 0.31541242 | K93: =IFERROR(K92/K26,0) -> 0.31483561 | L93: =IFERROR(L92/L26,0) -> 0.31901549 | ... P93: =IFERROR(P92/P26,0) -> 0.33873871

Sheet AR Unformatted HF
A1: Aster Ridge Senior Living (DEMO)
A2: T12 Income Statement -- Jul 2025 through Jun 2026
A3: SYNTHETIC DEMO DATA -- NOT A REAL COMMUNITY. All figures fabricated for demonstration/testing purposes only.
A5: Acct | B5: Description | C5: 45869 | D5: 45900 | E5: 45930 | F5: 45961 | G5: 45991 | H5: 46022 | I5: 46053 | J5: 46081 | K5: 46112 | L5: 46142 | M5: 46173 | N5: 46203 | O5: Total
B6: REVENUE
A7: 4010 | B7: Rent Income - IL | C7: 130152 | D7: 130398 | E7: 133507 | F7: 132350 | G7: 135400 | H7: 135680 | I7: 136760 | J7: 133994 | K7: 138063 | L7: 137300 | M7: 139892 | N7: 140535 | O7: 1624031
A8: 4020 | B8: Rent Income - AL | C8: 120910 | D8: 125160 | E8: 124124 | F8: 118673 | G8: 123170 | H8: 128565 | I8: 129671 | J8: 125562 | K8: 125145 | L8: 128700 | M8: 127791 | N8: 128925 | O8: 1506396
A9: 4030 | B9: Rent Income - MC | C9: 86707 | D9: 93912 | E9: 93135 | F9: 92846 | G9: 101036 | H9: 94072 | I9: 94660 | J9: 102463 | K9: 101721 | L9: 93124 | M9: 100585 | N9: 101595 | O9: 1155856
A10: 4110 | B10: Care Level Income - AL | C10: 25794 | D10: 26554 | E10: 26411 | F10: 25486 | G10: 26677 | H10: 27880 | I10: 27928 | J10: 26782 | K10: 26550 | L10: 27389 | M10: 27449 | N10: 27660 | O10: 322560
A11: 4120 | B11: Care Level Income - MC | C11: 15207 | D11: 16471 | E11: 16462 | F11: 16569 | G11: 18104 | H11: 16781 | I11: 16726 | J11: 17969 | K11: 17842 | L11: 16463 | M11: 17953 | N11: 18000 | O11: 204547
A12: 4210 | B12: Second Person Fees | C12: 7297 | D12: 7396 | E12: 7551 | F12: 7493 | G12: 7787 | H12: 7905 | I12: 7847 | J12: 7539 | K12: 7638 | L12: 7795 | M12: 7986 | N12: 7960 | O12: 92194
A13: 4310 | B13: Community Fees | C13: 4087 | D13: 9901 | E13: 5616 | F13: 3000 | G13: 13391 | H13: 3969 | I13: 3000 | J13: 3000 | K13: 6430 | L13: 4092 | M13: 9873 | N13: 3000 | O13: 69359
A14: 4410 | B14: Other Resident Income | C14: 3577 | D14: 3254 | E14: 2852 | F14: 2960 | G14: 3420 | H14: 3557 | I14: 3171 | J14: 2827 | K14: 3029 | L14: 3481 | M14: 3521 | N14: 3091 | O14: 38740
A15: 4510 | B15: Guest Meals & Ancillary | C15: 2517 | D15: 1915 | E15: 2183 | F15: 2715 | G15: 2310 | H15: 1882 | I15: 2397 | J15: 2693 | K15: 2102 | L15: 1958 | M15: 2586 | N15: 2568 | O15: 27826
B16: TOTAL REVENUE | C16: 396248 | D16: 414961 | E16: 411841 | F16: 402092 | G16: 431295 | H16: 420291 | I16: 422160 | J16: 422829 | K16: 428520 | L16: 420302 | M16: 437636 | N16: 433334 | O16: 5041509
B18: OPERATING EXPENSES
A19: 6010 | B19: Caregiver Wages | C19: 45613 | D19: 45404 | E19: 44841 | F19: 44539 | G19: 44829 | H19: 45393 | I19: 45615 | J19: 45253 | K19: 44701 | L19: 44564 | M19: 44990 | N19: 45515 | O19: 541257
A20: 6020 | B20: Med Tech Wages | C20: 17206 | D20: 17028 | E20: 16842 | F20: 16850 | G20: 17044 | H20: 17212 | I20: 17170 | J20: 16964 | K20: 16820 | L20: 16894 | M20: 17106 | N20: 17224 | O20: 204360
A21: 6030 | B21: Wellness Director | C21: 5554 | D21: 5485 | E21: 5454 | F21: 5495 | G21: 5564 | H21: 5584 | I21: 5535 | J21: 5469 | K21: 5459 | L21: 5516 | M21: 5577 | N21: 5576 | O21: 66268
A22: 6110 | B22: Dining Wages | C22: 24823 | D22: 24567 | E22: 24610 | F22: 24904 | G22: 25129 | H22: 25038 | I22: 24731 | J22: 24543 | K22: 24680 | L22: 24992 | M22: 25137 | N22: 24958 | O22: 298112
A23: 6120 | B23: Dining Director | C23: 4749 | D23: 4728 | E23: 4768 | F23: 4826 | G23: 4838 | H23: 4791 | I23: 4736 | J23: 4734 | K23: 4786 | L23: 4836 | M23: 4829 | N23: 4773 | O23: 57394
A24: 6210 | B24: Housekeeping Wages | C24: 12278 | D24: 12315 | E24: 12466 | F24: 12567 | G24: 12507 | H24: 12352 | I24: 12271 | J24: 12353 | K24: 12508 | L24: 12567 | M24: 12465 | N24: 12314 | O24: 148963
A25: 6310 | B25: Maintenance Wages | C25: 8912 | D25: 8996 | E25: 9102 | F25: 9114 | G25: 9019 | H25: 8921 | I25: 8927 | J25: 9030 | K25: 9118 | L25: 9094 | M25: 8985 | N25: 8910 | O25: 108128
A26: 6410 | B26: Activities Wages | C26: 6209 | D26: 6286 | E26: 6331 | F26: 6294 | G26: 6215 | H26: 6181 | I26: 6229 | J26: 6306 | K26: 6328 | L26: 6271 | M26: 6198 | N26: 6187 | O26: 75035
A27: 6510 | B27: Concierge Wages | C27: 7536 | D27: 7621 | E27: 7621 | F27: 7537 | G27: 7460 | H27: 7475 | I27: 7565 | J27: 7632 | K27: 7603 | L27: 7509 | M27: 7454 | N27: 7497 | O27: 90510
A28: 6610 | B28: Business Office Manager | C28: 5183 | D28: 5214 | E28: 5177 | F28: 5113 | G28: 5091 | H28: 5136 | I28: 5198 | J28: 5210 | K28: 5159 | L28: 5100 | M28: 5098 | N28: 5155 | O28: 61834
A29: 6620 | B29: Executive Director | C29: 8555 | D29: 8545 | E29: 8446 | F29: 8367 | G29: 8394 | H29: 8497 | I29: 8565 | J29: 8522 | K29: 8416 | L29: 8362 | M29: 8420 | N29: 8526 | O29: 101615
A30: 6630 | B30: Sales & Marketing Wages | C30: 7075 | D30: 7019 | E30: 6933 | F30: 6912 | G30: 6978 | H30: 7059 | I30: 7067 | J30: 6993 | K30: 6918 | L30: 6924 | M30: 7005 | N30: 7072 | O30: 83955
... A48: 7990 | B48: Other G&A | C48: 4128 | D48: 4162 | E48: 4340 | F48: 4296 | G48: 4120 | H48: 4175 | I48: 4347 | J48: 4282 | K48: 4114 | L48: 4189 | M48: 4353 | N48: 4268 | O48: 50774
B49: TOTAL OPERATING EXPENSES | C49: 285823 | D49: 286326 | E49: 283277 | F49: 281884 | G49: 285001 | H49: 287726 | I49: 289249 | J49: 287940 | K49: 285361 | L49: 283040 | M49: 284503 | N49: 286547 | O49: 3426677
B51: NET OPERATING INCOME | C51: 110425 | D51: 128635 | E51: 128564 | F51: 120208 | G51: 146294 | H51: 132565 | I51: 132911 | J51: 134889 | K51: 143159 | L51: 137262 | M51: 153133 | N51: 146787 | O51: 1614832
